Workbook
Name Balcheck: 'MODEL&SCHEDULE'!$D$234
Name Base_Year: 'HISTORICAL FS'!$I$5
Name circularity: COVER!$C$21
Name Forecast_year: ASSUMPTIONS!$D$22
Name L_Scenarios: SCENARIOS!$C$15:$C$17
Name S_Scenario: SCENARIOS!$D$8

Sheet COVER
B6: NEXT PLC | F6: 3 STATEMENT FINANCIAL MODEL
E8: -
G10: Equity Research | Initiating Coverage
H11: ="FINANCIAL MODEL FOR " &Base_Year +1& " to " & Forecast_year+Base_Year -> FINANCIAL MODEL FOR 2027 to 2031
B15: Analyst : | C15: Oyindamola Aribilola
B17: Date : | C17: 46167
B19: Version : | C19: Ver 1.0
B21: Circularity Switch : | C21: 2
A30: Aim : | B30: To examine the firm's financial projections along with its competitors to determine if it is a SMART investment or not

Sheet SUMMARY
C1: KPI | K1: =SCENARIOS!K1 -> CURRENTLY RUNNING: BULL / BEST CASE
M2: ='HISTORICAL FS'!L2 -> NEXT PLC
M3: ='HISTORICAL FS'!L3 -> Bal Check: OK
G4: =ASSUMPTIONS!G4 -> 45322 | H4: =ASSUMPTIONS!H4 -> 45688 | I4: =ASSUMPTIONS!I4 -> 46053 | J4: =ASSUMPTIONS!J4 -> 46418 | K4: =ASSUMPTIONS!K4 -> 46783 | L4: =ASSUMPTIONS!L4 -> 47149 | M4: =ASSUMPTIONS!M4 -> 47514 | N4: =ASSUMPTIONS!N4 -> 47879
G5: =ASSUMPTIONS!G5 -> 2024 | H5: =ASSUMPTIONS!H5 -> 2025 | I5: =ASSUMPTIONS!I5 -> 2026 | J5: =ASSUMPTIONS!J5 -> 2027 | K5: =ASSUMPTIONS!K5 -> 2028 | L5: =ASSUMPTIONS!L5 -> 2029 | M5: =ASSUMPTIONS!M5 -> 2030 | N5: =ASSUMPTIONS!N5 -> 2031
D6: Units | E6: Trend
B7: Revenue
C8: ='MODEL&SCHEDULE'!C17 -> Revenue | D8: $MM | G8: ='MODEL&SCHEDULE'!G17 -> 5491 | H8: ='MODEL&SCHEDULE'!H17 -> 6118.1 | I8: ='MODEL&SCHEDULE'!I17 -> 6901.3 | J8: ='MODEL&SCHEDULE'!J17 -> 7275.704 | K8: ='MODEL&SCHEDULE'!K17 -> 7952.2216 | L8: ='MODEL&SCHEDULE'!L17 -> 8824.7422 | M8: ='MODEL&SCHEDULE'!M17 -> 9622.7977 | N8: ='MODEL&SCHEDULE'!N17 -> 10418.633
C9: Revenue Growth | D9: % | H9: =IFERROR(H8/G8-1,0) -> 0.11420506 | I9: =IFERROR(I8/H8-1,0) -> 0.1280136 | J9: =IFERROR(J8/I8-1,0) -> 0.054251228 | K9: =IFERROR(K8/J8-1,0) -> 0.092983118 | L9: =IFERROR(L8/K8-1,0) -> 0.10972036 | M9: =IFERROR(M8/L8-1,0) -> 0.090433853 | N9: =IFERROR(N8/M8-1,0) -> 0.082703069
B12: EBITDA
C13: ='MODEL&SCHEDULE'!C67 -> EBITDA | D13: $MM | G13: ='MODEL&SCHEDULE'!G67 -> 1211.1 | H13: ='MODEL&SCHEDULE'!H67 -> 1363.9 | I13: ='MODEL&SCHEDULE'!I67 -> 1574.5 | J13: ='MODEL&SCHEDULE'!J67 -> 1688.1824 | K13: ='MODEL&SCHEDULE'!K67 -> 1835.0381 | L13: ='MODEL&SCHEDULE'!L67 -> 2017.8368 | M13: ='MODEL&SCHEDULE'!M67 -> 2186.1258 | N13: ='MODEL&SCHEDULE'!N67 -> 2353.4501
C14: EBITDA Growth | D14: % | H14: =IFERROR(H13/G13-1,0) -> 0.1261663 | I14: =IFERROR(I13/H13-1,0) -> 0.15441015 | J14: =IFERROR(J13/I13-1,0) -> 0.072202198 | K14: =IFERROR(K13/J13-1,0) -> 0.086990474 | L14: =IFERROR(L13/K13-1,0) -> 0.099615734 | M14: =IFERROR(M13/L13-1,0) -> 0.083400708 | N14: =IFERROR(N13/M13-1,0) -> 0.07653919
C15: ='MODEL&SCHEDULE'!C78 -> EBITDA margin | D15: % | G15: ='MODEL&SCHEDULE'!G78 -> 0.22056092 | H15: ='MODEL&SCHEDULE'!H78 -> 0.22292869 | I15: ='MODEL&SCHEDULE'!I78 -> 0.22814542 | J15: ='MODEL&SCHEDULE'!J78 -> 0.2320301 | K15: ='MODEL&SCHEDULE'!K78 -> 0.23075792 | L15: ='MODEL&SCHEDULE'!L78 -> 0.22865674 | M15: ='MODEL&SCHEDULE'!M78 -> 0.22718194 | N15: ='MODEL&SCHEDULE'!N78 -> 0.22588858
B18: EBIT
C19: ='MODEL&SCHEDULE'!C64 -> EBIT | D19: $MM | G19: ='MODEL&SCHEDULE'!G64 -> 970.5 | H19: ='MODEL&SCHEDULE'!H64 -> 1075 | I19: ='MODEL&SCHEDULE'!I64 -> 1272 | J19: ='MODEL&SCHEDULE'!J64 -> 1380.5705 | K19: ='MODEL&SCHEDULE'!K64 -> 1509.3565 | L19: ='MODEL&SCHEDULE'!L64 -> 1675.3355 | M19: ='MODEL&SCHEDULE'!M64 -> 1827.4274 | N19: ='MODEL&SCHEDULE'!N64 -> 1979.3134
C20: EBIT Growth | D20: % | H20: =IFERROR(H19/G19-1,0) -> 0.10767646 | I20: =IFERROR(I19/H19-1,0) -> 0.18325581 | J20: =IFERROR(J19/I19-1,0) -> 0.085354152 | K20: =IFERROR(K19/J19-1,0) -> 0.093284673 | L20: =IFERROR(L19/K19-1,0) -> 0.10996672 | M20: =IFERROR(M19/L19-1,0) -> 0.090782958 | N20: =IFERROR(N19/M19-1,0) -> 0.083114624
C21: ='MODEL&SCHEDULE'!C77 -> EBIT margin | D21: % | G21: ='MODEL&SCHEDULE'!G77 -> 0.17674376 | H21: ='MODEL&SCHEDULE'!H77 -> 0.17570814 | I21: ='MODEL&SCHEDULE'!I77 -> 0.1843131 | J21: ='MODEL&SCHEDULE'!J77 -> 0.18975078 | K21: ='MODEL&SCHEDULE'!K77 -> 0.18980313 | L21: ='MODEL&SCHEDULE'!L77 -> 0.18984527 | M21: ='MODEL&SCHEDULE'!M77 -> 0.18990605 | N21: ='MODEL&SCHEDULE'!N77 -> 0.18997823
B24: EBIAT
C25: ='MODEL&SCHEDULE'!C73 -> EBIAT/NOPAT | D25: $MM | G25: ='MODEL&SCHEDULE'!G73 -> 727.875 | H25: ='MODEL&SCHEDULE'!H73 -> 806.25 | I25: ='MODEL&SCHEDULE'!I73 -> 954 | J25: ='MODEL&SCHEDULE'!J73 -> 1035.4279 | K25: ='MODEL&SCHEDULE'!K73 -> 1132.0174 | L25: ='MODEL&SCHEDULE'!L73 -> 1256.5016 | M25: ='MODEL&SCHEDULE'!M73 -> 1370.5706 | N25: ='MODEL&SCHEDULE'!N73 -> 1484.485
C26: EBIAT Growth | D26: % | H26: =IFERROR(H25/G25-1,0) -> 0.10767646 | I26: =IFERROR(I25/H25-1,0) -> 0.18325581 | J26: =IFERROR(J25/I25-1,0) -> 0.085354152 | K26: =IFERROR(K25/J25-1,0) -> 0.093284673 | L26: =IFERROR(L25/K25-1,0) -> 0.10996672 | M26: =IFERROR(M25/L25-1,0) -> 0.090782958 | N26: =IFERROR(N25/M25-1,0) -> 0.083114624
C27: ='MODEL&SCHEDULE'!C79 -> EBIAT/NOPAT margin | D27: % | G27: ='MODEL&SCHEDULE'!G79 -> 0.13255782 | H27: ='MODEL&SCHEDULE'!H79 -> 0.13178111 | I27: ='MODEL&SCHEDULE'!I79 -> 0.13823483 | J27: ='MODEL&SCHEDULE'!J79 -> 0.14231308 | K27: ='MODEL&SCHEDULE'!K79 -> 0.14235235 | L27: ='MODEL&SCHEDULE'!L79 -> 0.14238395 | M27: ='MODEL&SCHEDULE'!M79 -> 0.14242953 | N27: ='MODEL&SCHEDULE'!N79 -> 0.14248367
B31: Net Income
C32: ='MODEL&SCHEDULE'!C71 -> Recurring Net Income | D32: $MM | G32: ='MODEL&SCHEDULE'!G71 -> 868.9 | H32: ='MODEL&SCHEDULE'!H71 -> 742.9 | I32: ='MODEL&SCHEDULE'!I71 -> 892.9 | J32: ='MODEL&SCHEDULE'!J71 -> 1052.7284 | K32: ='MODEL&SCHEDULE'!K71 -> 1150.7809 | L32: ='MODEL&SCHEDULE'!L71 -> 1284.0156 | M32: ='MODEL&SCHEDULE'!M71 -> 1399.7976 | N32: ='MODEL&SCHEDULE'!N71 -> 1520.7002
C33: Net Income Growth | D33: % | H33: =IFERROR(H32/G32-1,0) -> -0.14501093 | I33: =IFERROR(I32/H32-1,0) -> 0.20191143 | J33: =IFERROR(J32/I32-1,0) -> 0.17899926 | K33: =IFERROR(K32/J32-1,0) -> 0.093141285 | L33: =IFERROR(L32/K32-1,0) -> 0.11577763 | M33: =IFERROR(M32/L32-1,0) -> 0.090171822 | N33: =IFERROR(N32/M32-1,0) -> 0.086371449
C34: ='MODEL&SCHEDULE'!C84 -> Recurring NI margin | D34: % | H34: ='MODEL&SCHEDULE'!H84 -> 0.12142659 | I34: ='MODEL&SCHEDULE'!I84 -> 0.12938142 | J34: ='MODEL&SCHEDULE'!J84 -> 0.14469094 | K34: ='MODEL&SCHEDULE'!K84 -> 0.14471188 | L34: ='MODEL&SCHEDULE'!L84 -> 0.14550177 | M34: ='MODEL&SCHEDULE'!M84 -> 0.14546681 | N34: ='MODEL&SCHEDULE'!N84 -> 0.14595967
B37: Dupont Analysis
C38: ='MODEL&SCHEDULE'!C87 -> Return on Equity | D38: ='MODEL&SCHEDULE'!D87 -> % | H38: ='MODEL&SCHEDULE'!H87 -> 0.43788866 | I38: ='MODEL&SCHEDULE'!I87 -> 0.50520539 | J38: ='MODEL&SCHEDULE'!J87 -> 0.54067219 | K38: ='MODEL&SCHEDULE'!K87 -> 0.50579958 | L38: ='MODEL&SCHEDULE'!L87 -> 0.47686312 | M38: ='MODEL&SCHEDULE'!M87 -> 0.43835069 | N38: ='MODEL&SCHEDULE'!N87 -> 0.40841995
C39: ='MODEL&SCHEDULE'!C84 -> Recurring NI margin | D39: ='MODEL&SCHEDULE'!D84 -> % | H39: ='MODEL&SCHEDULE'!H84 -> 0.12142659 | I39: ='MODEL&SCHEDULE'!I84 -> 0.12938142 | J39: ='MODEL&SCHEDULE'!J84 -> 0.14469094 | K39: ='MODEL&SCHEDULE'!K84 -> 0.14471188 | L39: ='MODEL&SCHEDULE'!L84 -> 0.14550177 | M39: ='MODEL&SCHEDULE'!M84 -> 0.14546681 | N39: ='MODEL&SCHEDULE'!N84 -> 0.14595967
C40: ='MODEL&SCHEDULE'!C85 -> Asset Turnover | D40: ='MODEL&SCHEDULE'!D85 -> Multiple | H40: ='MODEL&SCHEDULE'!H85 -> 1.2750292 | I40: ='MODEL&SCHEDULE'!I85 -> 1.4101841 | J40: ='MODEL&SCHEDULE'!J85 -> 1.4492829 | K40: ='MODEL&SCHEDULE'!K85 -> 1.4881154 | L40: ='MODEL&SCHEDULE'!L85 -> 1.5294244 | M40: ='MODEL&SCHEDULE'!M85 -> 1.5139156 | N40: ='MODEL&SCHEDULE'!N85 -> 1.4711132
C41: ='MODEL&SCHEDULE'!C86 -> Financial leverage | D41: ='MODEL&SCHEDULE'!D86 -> Multiple | H41: ='MODEL&SCHEDULE'!H86 -> 2.8283281 | I41: ='MODEL&SCHEDULE'!I86 -> 2.7689827 | J41: ='MODEL&SCHEDULE'!J86 -> 2.5783361 | K41: ='MODEL&SCHEDULE'!K86 -> 2.3487548 | L41: ='MODEL&SCHEDULE'!L86 -> 2.142878 | M41: ='MODEL&SCHEDULE'!M86 -> 1.9904722 | N41: ='MODEL&SCHEDULE'!N86 -> 1.9020765
C43: ='MODEL&SCHEDULE'!C81 -> Return on Asset | D43: ='MODEL&SCHEDULE'!D81 -> % | H43: ='MODEL&SCHEDULE'!H81 -> 0.15482244 | I43: ='MODEL&SCHEDULE'!I81 -> 0.18245162 | J43: ='MODEL&SCHEDULE'!J81 -> 0.20969811 | K43: ='MODEL&SCHEDULE'!K81 -> 0.21534797 | L43: ='MODEL&SCHEDULE'!L81 -> 0.22253395 | M43: ='MODEL&SCHEDULE'!M81 -> 0.22022447 | N43: ='MODEL&SCHEDULE'!N81 -> 0.2147232

Sheet HISTORICAL FS
C1: ANNUAL REPORT | K1: =SCENARIOS!K1 -> CURRENTLY RUNNING: BULL / BEST CASE
L2: =COVER!B6 -> NEXT PLC
L3: ='MODEL&SCHEDULE'!M3 -> Bal Check: OK
E4: =DATE(YEAR(F4)-1,MONTH(F4),DAY(F4)) -> 44592 | F4: =DATE(YEAR(G4)-1,MONTH(G4),DAY(G4)) -> 44957 | G4: =DATE(YEAR(H4)-1,MONTH(H4),DAY(H4)) -> 45322 | H4: =DATE(YEAR(I4)-1,MONTH(I4),DAY(I4)) -> 45688 | I4: 46053 | J4: =DATE(YEAR(I4)+1,MONTH(I4),DAY(I4)) -> 46418 | K4: =DATE(YEAR(J4)+1,MONTH(J4),DAY(J4)) -> 46783 | L4: =DATE(YEAR(K4)+1,MONTH(K4),DAY(K4)) -> 47149 | M4: =DATE(YEAR(L4)+1,MONTH(L4),DAY(L4)) -> 47514 | N4: =DATE(YEAR(M4)+1,MONTH(M4),DAY(M4)) -> 47879
E5: =2022 -> 2022 | F5: =E5+1 -> 2023 | G5: =F5+1 -> 2024 | H5: =G5+1 -> 2025 | I5: =H5+1 -> 2026
B7: Millions for the Year Ended January 31
C8: INCOME STATEMENT
B9: Continuing Operations
C10: revenue | E10: 4376.5 | F10: 5034 | G10: 5491 | H10: 6118.1 | I10: 6901.3
C11: credit account interest | E11: 249.4
C12: Revenue | E12: =E10+E11 -> 4625.9 | F12: =F10+F11 -> 5034 | G12: =G10+G11 -> 5491 | H12: =H10+H11 -> 6118.1 | I12: =I10+I11 -> 6901.3
C13: cost of sales | E13: 2625.3 | F13: 2827.7 | G13: 3034.5 | H13: 3456.5 | I13: 3847.5
C14: impairment losses on customer and other receivables | E14: 28.6 | F14: 31 | G14: 36 | H14: 19.4 | I14: 7.1
C15: Gross profit/(loss) | E15: =E12-E13-E14 -> 1972 | F15: =F12-F13-F14 -> 2175.3 | G15: =G12-G13-G14 -> 2420.5 | H15: =H12-H13-H14 -> 2642.2 | I15: =I12-I13-I14 -> 3046.7
C16: Distribution costs | E16: 693.7 | F16: 750 | G16: 794.1 | H16: 878.8 | I16: 1027.1
C17: Administrative expenses | E17: 380.2 | F17: 481.8 | G17: 657.7 | H17: 670.6 | I17: 742.4
C18: other losses/Gain-on financial instruments | E18: 2.5 | F18: -16.3 | G18: 12.3 | H18: 3.4 | I18: -3.4
C19: Trading profit | E19: =E15-E16-E17+E18 -> 900.6 | F19: =F15-F16-F17+F18 -> 927.2 | G19: =G15-G16-G17+G18 -> 981 | H19: =H15-H16-H17+H18 -> 1096.2 | I19: =I15-I16-I17+I18 -> 1273.8
C20: share of results of associates and joint ventures | E20: 4.8 | F20: 14.3 | G20: 6.9 | H20: 6.7 | I20: 7.9
C21: Impairment in associates and joint ventures | H21: -13 | I21: -2.9
C22: Exceptional items- curtailment loss | H22: -14.5
C23: Operating profit/(loss) | E23: =SUM(E19:E22) -> 905.4 | F23: =SUM(F19:F22) -> 941.5 | G23: =SUM(G19:G22) -> 987.9 | H23: =SUM(H19:H22) -> 1075.4 | I23: =SUM(I19:I22) -> 1278.8
C24: Gain on Reiss transaction- exceptional items | G24: 108.6
C25: Finance income | E25: 4.2 | F25: 5.7 | G25: 6.8 | H25: 8.2 | I25: 11
C26: finance costs | E26: -86.5 | F26: -77.9 | G26: -87.5 | H26: -96.6 | I26: -97.2
C27: Profit before taxation | E27: =SUM(E23:E26) -> 823.1 | F27: =SUM(F23:F26) -> 869.3 | G27: =SUM(G23:G26) -> 1015.8 | H27: =SUM(H23:H26) -> 987 | I27: =SUM(I23:I26) -> 1192.6
C28: Taxation | E28: -145.6 | F28: -158.6 | G28: -215.3 | H28: -243.8 | I28: -294.6
C29: Net Profit | E29: =SUM(E27:E28) -> 677.5 | F29: =SUM(F27:F28) -> 710.7 | G29: =SUM(G27:G28) -> 800.5 | H29: =SUM(H27:H28) -> 743.2 | I29: =SUM(I27:I28) -> 898
C32: Profit attributable to:
C33: Equity holders of the parent company | E33: 677.5 | F33: 711.7 | G33: 802.3 | H33: 736.1 | I33: 888.5
C34: non controlling interests | F34: -1 | G34: -1.8 | H34: 7.1 | I34: 9.5
E35: =SUM(E33:E34) -> 677.5 | F35: =SUM(F33:F34) -> 710.7 | G35: =SUM(G33:G34) -> 800.5 | H35: =SUM(H33:H34) -> 743.2 | I35: =SUM(I33:I34) -> 898
C36: Earnings/(losses) per share
C37: Basic | E37: 530.8p | F37: 573.4p | G37: 661.6p | H37: 615.1p | I37: 760.1p
C38: diluted | E38: 524.0p | F38: 570.5p | G38: 655.9p | H38: 605.5p | I38: 745.4p
C46: CASH-FLOW
C47: Cash flows from operating activities
C48: Operating profit | E48: 905.4 | F48: 941.5 | G48: 987.9 | H48: 1075.4 | I48: 1278.8
C49: Profit on disposal of associate | I49: -16.3
C50: Depreciation, impairment and (profit)/loss on disposal of property, plant and equipment | E50: 90.3 | F50: 80.6 | G50: 95.7 | H50: 117.9 | I50: 119.2
C51: Depreciation and impairment on right-of-use assets | E51: 112.6 | F51: 72.7 | G51: 111.8 | H51: 137.9 | I51: 156.4
C52: Amortisation and impairment of intangible assets | E52: 4.3 | F52: 12.5 | G52: 38.5 | H52: 55.2 | I52: 59.1
C53: Amortisation, impairemnt & disposals of investments | F53: 1.1 | G53: 0.8 | H53: 13.5 | I53: 5.6
C54: Share option charge | E54: 19.9 | F54: 24.3 | G54: 31.9 | H54: 40.9 | I54: 43.1
C55: Share of profit of associates and joint ventures | E55: -4.8 | F55: -14.3 | G55: -6.9 | H55: -6.7 | I55: -7.9
C56: Exchange movement | E56: -1.6 | F56: -0.8 | G56: -15.5 | H56: -5.6 | I56: 5.5
C57: Increase in inventories and right of return asset | E57: -96.5 | F57: -22.8 | G57: 15.3 | H57: -100.3 | I57: -79.2
C58: (Increase)/decrease in customer and other receivables | E58: -165.4 | F58: -156.5 | G58: 3.7 | H58: -52.3 | I58: -153.7
C59: Increase/(decrease) in trade and other payables | E59: 235.2 | F59: 12 | G59: 47.6 | H59: 93.2 | I59: 45.9
C60: Net pension contributions less income statement charge | E60: -2.7
C61: Interest received | G61: 2.8 | H61: 7.4 | I61: 10.2
C62: Cash flow from Operations | E62: 1096.7 | F62: 950.3 | G62: 1313.6 | H62: 1376.5 | I62: 1466.7
C63: corporation tax paid | E63: -125.3 | F63: -151.5 | G63: -193.3 | H63: -242.6 | I63: -233.1
C64: Net cash from Operating activities | E64: =SUM(E62:E63) -> 971.4 | F64: =SUM(F62:F63) -> 798.8 | G64: =SUM(G62:G63) -> 1120.3 | H64: =SUM(H62:H63) -> 1133.9 | I64: =SUM(I62:I63) -> 1233.6
C65: Cashflow from Investing activities
C66: Additions to PPE | E66: -239.2 | F66: -207.1 | G66: -160.9 | H66: -122.9 | I66: -139.6
C67: Movements in Capital accruals | E67: -4.4 | F67: 2 | G67: 23.9 | H67: -6.4 | I67: 4.2
C68: Payments to acquire PPE | E68: =SUM(E66:E67) -> -243.6 | F68: =SUM(F66:F67) -> -205.1 | G68: =SUM(G66:G67) -> -137 | H68: =SUM(H66:H67) -> -129.3 | I68: =SUM(I66:I67) -> -135.4
C69: Proceeds from sale of PPE | E69: 3.4 | G69: 2 | H69: 2.6 | I69: 0.4
C70: Proceeds from sale of held for sale assets | E70: 15.5 | F70: 41.7 | G70: 3.3 | I70: 55.7
C71: purchase of intangible assets | E71: -22.7 | F71: -41 | G71: -51.2 | H71: -28.2 | I71: -35.8
C72: Amounts loaned/repaid to Joint ventures and associates | E72: -10.8 | F72: 11.3 | H72: -0.9 | I72: -4.8
C73: Disposal of other investment | F73: 1.8
C74: Disposal of minority interest
C75: Investment in subsidiaries | F75: -28.8 | G75: -153.2 | H75: -24.2
C76: Investment in associates and joint ventures | E76: -34.3 | F76: -64.7 | G76: -0.9 | H76: -1.2
C77: Acquisition of other investments | F77: -1.9
C78: Dividend from jointly controlled entity | F78: 9.8 | G78: 2.6
C79: Disposal of preference shares in jointly controlled entity | F79: 5.5
C80: Net cash from Investing activities | E80: =SUM(E68:E78) -> -292.5 | F80: =SUM(F68:F78) -> -276.9 | G80: =SUM(G68:G78) -> -334.4 | H80: =SUM(H68:H78) -> -181.2 | I80: =SUM(I68:I78) -> -119.9
C81: Cashflows from financing activities
C82: Repurchase of own shares | E82: -8.7 | F82: -228.5 | G82: -177.3 | H82: -360.2 | I82: -131.4
C83: purchase of shares by ESOT | E83: -151.3 | F83: -124 | G83: -116.3 | H83: -126.8 | I83: -169
C84: Disposal of shares by ESOT | E84: 72.5 | F84: 34.3 | G84: 97.8 | H84: 77 | I84: 107.2
C85: Purchase of equity from Non controlling interests | H85: -5 | I85: -1.5
C86: Issue of shares in subsidiaries to non controlling interests | H86: 0.5
C87: Repayment of Loans | G87: -2.5 | H87: -2.4 | I87: -31.5
C88: Drawdown of revolving credit facility | I88: 60
C89: Incentives received for leases within the scope of IFRS 16 | E89: 11.9 | F89: 0.1 | H89: 1 | I89: 0.7
C90: Lease payments | E90: -172.3 | F90: -157.1 | G90: -156.1 | H90: -164.6 | I90: -167.4
C91: Interest paid(including lease interest) | E91: -91.1 | F91: -74.1 | G91: -79.2 | H91: -93.3 | I91: -94.1
C92: Interest received | E92: 0.8 | F92: 0.3
C93: Repayment of corporate bonds | E93: -325 | I93: -386.4
C94: Issue of corporate bonds | I94: 298.4
C95: Return of capital via B share scheme | I95: -421.5
C96: Proceeds from sale and leaseback transactions | E96: 14.3 | F96: 59.3 | G96: 18.6
C97: Dividends paid to owners of NEXT plc | E97: -344.5 | F97: -237.4 | G97: -248.3 | H97: -257.8 | I97: -286.5
C98: Dividends paid to Non controlling interests in subsidiaries | H98: -8 | I98: -2
C99: Net cash from financing activities | E99: =SUM(E82:E98) -> -993.4 | F99: =SUM(F82:F98) -> -727.1 | G99: =SUM(G82:G98) -> -663.3 | H99: =SUM(H82:H98) -> -939.6 | I99: =SUM(I82:I98) -> -1225
C100: Net (decrease)/increase in cash and cash equivalents | E100: =E99+E80+E64 -> -314.5 | F100: =F99+F80+F64 -> -205.2 | G100: =G99+G80+G64 -> 122.6 | H100: =H99+H80+H64 -> 13.1 | I100: =I99+I80+I64 -> -111.3
C101: Opening cash and cash equivalenrs | E101: 514.8 | F101: 199.9 | G101: 2.7 | H101: 124.3 | I101: 171.3
C102: exclude bank loans | H102: 33.9
C103: effect of exchange rate fluctuations on cash held | E103: -0.4 | F103: 2.5 | G103: -1 | I103: 0.2
C104: closing cash and cash equivalents | E104: =SUM(E100:E103) -> 199.9 | F104: =SUM(F100:F103) -> -2.8 | G104: =SUM(G100:G103) -> 124.3 | H104: =SUM(H100:H103) -> 171.3 | I104: =SUM(I100:I103) -> 60.2
C107: BALANCE SHEET
C111: NON-CURRENT ASSETS
C112: Property Plant & Equipment | E112: 601.1 | F112: 644.8 | G112: 687.5 | H112: 686.4 | I112: 667.7
C113: Intangible Assets | E113: 79.3 | F113: 137.1 | G113: 757.2 | H113: 735.4 | I113: 713.7
C114: Right-of-Use Assets | E114: 639.1 | F114: 662 | G114: 734.6 | H114: 737.3 | I114: 733.1
C115: Associates, joint ventures and other investments | E115: 46.2 | F115: 114.6 | G115: 38 | H115: 32.7 | I115: 35.2
...

Sheet ASSUMPTIONS
C1: INPUT & ASSUMPTIONS | K1: =SCENARIOS!K1 -> CURRENTLY RUNNING: BULL / BEST CASE
M2: =COVER!B6 -> NEXT PLC
M3: ='MODEL&SCHEDULE'!M3 -> Bal Check: OK
E4: ='HISTORICAL FS'!E4 -> 44592 | F4: ='HISTORICAL FS'!F4 -> 44957 | G4: ='HISTORICAL FS'!G4 -> 45322 | H4: ='HISTORICAL FS'!H4 -> 45688 | I4: ='HISTORICAL FS'!I4 -> 46053 | J4: ='HISTORICAL FS'!J4 -> 46418 | K4: ='HISTORICAL FS'!K4 -> 46783 | L4: ='HISTORICAL FS'!L4 -> 47149 | ... N4: ='HISTORICAL FS'!N4 -> 47879
E5: ='HISTORICAL FS'!E5 -> 2022 | F5: ='HISTORICAL FS'!F5 -> 2023 | G5: ='HISTORICAL FS'!G5 -> 2024 | H5: ='HISTORICAL FS'!H5 -> 2025 | I5: ='HISTORICAL FS'!I5 -> 2026 | J5: =I5+1 -> 2027 | K5: =J5+1 -> 2028 | L5: =K5+1 -> 2029 | M5: =L5+1 -> 2030 | N5: =M5+1 -> 2031
C6: Line item description | D6: Notes/ source
C7: Days in the period | E7: =DATE(E5,12,31)-DATE(E5,1,1)+1 -> 365 | F7: =DATE(F5,12,31)-DATE(F5,1,1)+1 -> 365 | G7: =DATE(G5,12,31)-DATE(G5,1,1)+1 -> 366 | H7: =DATE(H5,12,31)-DATE(H5,1,1)+1 -> 365 | I7: =DATE(I5,12,31)-DATE(I5,1,1)+1 -> 365 | J7: =DATE(J5,12,31)-DATE(J5,1,1)+1 -> 365 | K7: =DATE(K5,12,31)-DATE(K5,1,1)+1 -> 366 | L7: =DATE(L5,12,31)-DATE(L5,1,1)+1 -> 365 | ... N7: =DATE(N5,12,31)-DATE(N5,1,1)+1 -> 365
C8: Million | D8: 1000000
C9: Nominal value of shares(p) | D9: 0.1
C10: Months in a year | D10: 12
B12: COLOR CODING SYSTEM
C13: Hard input (only in Assumptions tab) | D13: Blue text, no fill
C14: Percent | D14: 0.1
C15: Linked input | D15: no fill
C16: Formula | D16: Black text, no fill
C17: Check | D17: no fill
C18: Error/warning/ important detail | D18: Red text
C19: Units | D19: [$'m]
C20: Multiple | D20: 10
B21: GENERAL
C22: Forecast Period | D22: 5
C23: Cases
C24: BULL / BEST CASE
C25: BASE CASE
C26: BEAR / WORST CASE
B30: MACROECONOMIC ASSUMPTIONS
C31: UK GDP Growth Rate
C32: UK CPI Inflation
C33: BoE Base Rate
C34: Consumer Confidence
A36: INCOME STATEMENT ASSUMPTIONS
B37: REVENUE ASSUMPTIONS
C38: ='rough sheet'!C1045 -> SEGMENT
C39: ='rough sheet'!C1046 -> Online UK | D39: % | J39: 0.05 | K39: 0.07 | L39: 0.124 | M39: 0.092 | N39: 0.069
C40: ='rough sheet'!C1049 -> Online (International) | D40: % | J40: 0.053 | K40: 0.08 | L40: 0.072 | M40: 0.086 | N40: 0.098
C42: ='rough sheet'!C1053 -> Retail stores | D42: % | J42: -0.015 | K42: 0.019 | L42: 0.032 | M42: 0.038 | N42: 0.05
C43: ='rough sheet'!C1057 -> Next Finance/credit account interest | D43: % | J43: -0.017487733 | K43: -0.037 | L43: 0.007 | M43: 0.028 | N43: 0.06
C44: ='rough sheet'!C1060 -> Total Platform +next sale of investment | D44: % | J44: -0.15014254 | K44: -0.0558 | L44: -0.02296982 | M44: 0.11 | N44: 0.04141509
C45: ='rough sheet'!C1066 -> Other business Activities | D45: % | J45: 0.080296157 | K45: 0.07 | L45: 0.0285 | M45: 0.004 | N45: 0.034166667
C48: Credit Sales as a % of Product Revenue | D48: % | J48: 0.47792652 | K48: 0.46 | L48: 0.45 | M48: 0.47 | N48: 0.46
B54: MARGIN ASSUMPTIONS
C55: Cost of sales as a % of revenue | D55: % | J55: 0.5608681
C56: Gross Margin % | D56: % | J56: 0.43451258
C57: Distribution Costs % Revenue | D57: % | J57: 0.14720635
C58: Admin Costs % Revenue | D58: % | J58: 0.10297191
C59: Operating costs % revenue | D59: %
B62: Income Tax Assumption
C63: UK corporation Tax rate | D63: Marginal Tax Rate | J63: 0.25
C64: current taxes % of total tax expense | D64: % | J64: 0.95177552
C65: Deferred Taxes % of Total tax expense | D65: % | J65: 0.048224479
C66: Reported ETR | D66: % | J66: 0.25
C67: Tax paid | D67: $MM | J67: 265
C68: Share option charge growth | D68: % | J68: 0.053789731
C69: Share of profit of results of Associates and JV | J69: 5.7997423 | K69: 6.7553392 | L69: 7.8683854 | M69: 9.1648232 | N69: 10.674869
A71: BALANCE SHEET ASSUMPTIONS
B73: WORKING CAPITAL ASSUMPTIONS
C74: Days Sales Outstanding (DSO) | D74: Days | J74: 170.23891 | K74: 175.80963 | L74: 180.41284 | M74: 178.21713 | N74: 180.8132
C75: Days Inventory Outstanding (DIO) | D75: Days | J75: 99.534975 | K75: 96.000779 | L75: 90.279249 | M75: 92.891408 | N75: 91.603913
C76: Days Payable Outstanding (DPO) | D76: Days | J76: 34.747341 | K76: 36.15935 | L76: 32.292111 | M76: 34.029824 | N76: 28.798094
C77: Current Operating Assets % revenues
C78: Current Operating Liabilities % revenues
C79: Working capital/other | J79: 75
C81: Customer Receivables and other Trade receiivables
C82: Customer receivables | D82: $MM | J82: 1323
C83: other receivables apart from customer receivables as a % of revenue | D83: % | J83: 0.033086988
C84: other receivables days using total revenue | J84: 12.083394
C85: other trade receivables(net of allowance) | D85: % | J85: 0.010609933
C86: prepayments | D86: % | J86: 0.01126923
C87: other debtors | D87: % | J87: 0.0073463443
C88: Amount due from associates and joint ventures | D88: % | J88: 0.0038614799
C90: Right to return as a % of inventory | D90: % | J90: 0.039996576
C92: Trade Payable and other liabilities
C93: Trade payables | D93: Days | J93: 34.747341 | K93: 26.15935 | L93: 32.292111 | M93: 34.029824 | N93: 28.798094
C94: Amounts owed to associates and JV | D94: % | J94: 0.00050127148
C95: Refund liabilities | D95: % | J95: 0.07130175 | K95: 0.073202103 | L95: 0.11389953 | M95: 0.12511848 | N95: 0.095880468
C97: Other taxation and social security | D97: % | J97: 0.12189372
C98: Deferred revenue from the sale of gift cards | D98: % | J98: 0.017223598
C99: Share based payment liability | D99: $MM | J99: 0.2
C101: other creditors and accruals
C102: staff related accruals | D102: % | J102: 0.086128616
C103: warehouse and duty related accruals | D103: % | J103: 0.0338308
C104: property accruals | D104: $MM | J104: 37.85
C105: marketing accruals | D105: % | J105: 0.0021323477
C106: unpaid interest on corporate bonds within accruals | D106: $MM | J106: 15.21861 | K106: 15.21861 | L106: 7.6093049 | M106: 7.6093049 | N106: 7.6093049
C107: Residual balance of accruals and other creditors | D107: $MM | J107: 201.9
C109: Total wages and Salaries a s a % of revenue | D109: % | J109: 0.15898883
B113: PPE& INTANGIBLES ASSSUMPTIONS
C114: Capex % Revenue | D114: % | M114: 0.031621517 | N114: 0.029760321
C115: Capex ($) | D115: $MM | J115: ='rough sheet'!J1406 -> 237 | K115: ='rough sheet'!K1406 -> 245 | L115: ='rough sheet'!L1406 -> 220 | M115: =M114*'MODEL&SCHEDULE'!M17 -> 304.28746 | N115: =N114*'MODEL&SCHEDULE'!N17 -> 310.06185
C117: D&A Prior year PP&E and intangible assets
C118: Dep as a % of prior year PPE | D118: % | J118: 0.16276988
C119: Dep as a % of prior year ROU | D119: % | J119: 0.18786536
C120: amortisation as a % of intangibles excld software | D120: % | J120: 0.050972391
C121: amortisation as a % of software | D121: % | J121: 0.36568619
C122: Amortisation as a % of intangibles incld Software | D122: % | J122: 0.13963822
C123: % of intangible excld software | D123: % | J123: 0.88946529
C124: % of software | J124: 0.11053471
C125: Total Capex incld software
C126: as a % of PPE | D126: % | J126: 0.82318758
C127: As a % of intangible | D127: % | J127: 0.17681242
...

Sheet SCENARIOS
C1: SCENARIO ANALYSIS | K1: =_xlfn.CONCAT( " CURRENTLY RUNNING: ", " ",INDEX(L_Scenarios,S_Scenario,1)) -> CURRENTLY RUNNING: BULL / BEST CASE
M2: =COVER!B6 -> NEXT PLC
M3: ='MODEL&SCHEDULE'!M3 -> Bal Check: OK
J4: ='MODEL&SCHEDULE'!J4 -> 46418 | K4: ='MODEL&SCHEDULE'!K4 -> 46783 | L4: ='MODEL&SCHEDULE'!L4 -> 47149 | M4: ='MODEL&SCHEDULE'!M4 -> 47514 | N4: ='MODEL&SCHEDULE'!N4 -> 47879
J5: ='MODEL&SCHEDULE'!J5 -> 2027 | K5: ='MODEL&SCHEDULE'!K5 -> 2028 | L5: ='MODEL&SCHEDULE'!L5 -> 2029 | M5: ='MODEL&SCHEDULE'!M5 -> 2030 | N5: ='MODEL&SCHEDULE'!N5 -> 2031
C8: SCENARIO SWITCH | D8: 1
C15: =ASSUMPTIONS!C24 -> BULL / BEST CASE
C16: =ASSUMPTIONS!C25 -> BASE CASE
C17: =ASSUMPTIONS!C26 -> BEAR / WORST CASE
C20: Sales :
C21: Online UK | J21: {=INDEX(J23:J25,S_Scenario)} -> 0.05 | K21: {=INDEX(K23:K25,S_Scenario)} -> 0.1 | L21: {=INDEX(L23:L25,S_Scenario)} -> 0.164 | M21: {=INDEX(M23:M25,S_Scenario)} -> 0.12 | N21: {=INDEX(N23:N25,S_Scenario)} -> 0.08
C23: =ASSUMPTIONS!C24 -> BULL / BEST CASE | J23: 0.05 | K23: 0.1 | L23: 0.164 | M23: 0.12 | N23: 0.08
C24: =ASSUMPTIONS!C25 -> BASE CASE | J24: 0.04500657 | K24: 0.07 | L24: 0.08 | M24: 0.102 | N24: 0.069
C25: =ASSUMPTIONS!C26 -> BEAR / WORST CASE | J25: 0.035 | K25: 0.04 | L25: 0.03 | M25: 0.05 | N25: 0.04
C29: Online UK International | J29: {=INDEX(J31:J33,S_Scenario)} -> 0.143 | K29: {=INDEX(K31:K33,S_Scenario)} -> 0.15 | L29: {=INDEX(L31:L33,S_Scenario)} -> 0.15 | M29: {=INDEX(M31:M33,S_Scenario)} -> 0.08 | N29: {=INDEX(N31:N33,S_Scenario)} -> 0.12
C31: =C23 -> BULL / BEST CASE | J31: 0.143 | K31: 0.15 | L31: 0.15 | M31: 0.08 | N31: 0.12
C32: =C24 -> BASE CASE | J32: 0.13903546 | K32: 0.08 | L32: 0.132 | M32: 0.056 | N32: 0.098
C33: =C25 -> BEAR / WORST CASE | J33: 0.04 | K33: 0.06 | L33: 0.1 | M33: 0.03 | N33: 0.04
C36: Finance Interest Income
J37: {=INDEX(J39:J41,S_Scenario)} -> 0.02 | K37: {=INDEX(K39:K41,S_Scenario)} -> 0.01 | L37: {=INDEX(L39:L41,S_Scenario)} -> 0.03 | M37: {=INDEX(M39:M41,S_Scenario)} -> 0.04 | N37: {=INDEX(N39:N41,S_Scenario)} -> 0.08
C39: =C31 -> BULL / BEST CASE | J39: 0.02 | K39: 0.01 | L39: 0.03 | M39: 0.04 | N39: 0.08
C40: =C32 -> BASE CASE | J40: -0.017487733 | K40: -0.037 | L40: 0.007 | M40: 0.028 | N40: 0.06
C41: =C33 -> BEAR / WORST CASE | J41: -0.04 | K41: -0.05 | L41: -0.03 | M41: 0 | N41: 0.03
C45: Retail | J45: {=INDEX(J47:J49,S_Scenario)} -> 0.01 | K45: {=INDEX(K47:K49,S_Scenario)} -> 0.03 | L45: {=INDEX(L47:L49,S_Scenario)} -> 0.048 | M45: {=INDEX(M47:M49,S_Scenario)} -> 0.005 | N45: {=INDEX(N47:N49,S_Scenario)} -> 0.07
C47: =C39 -> BULL / BEST CASE | J47: 0.01 | K47: 0.03 | L47: 0.048 | M47: 0.005 | N47: 0.07
C48: =C40 -> BASE CASE | J48: -0.020495233 | K48: 0.019 | L48: 0.032 | M48: -0.02 | N48: 0.05
C49: =C41 -> BEAR / WORST CASE | J49: -0.04 | K49: -0.02 | L49: 0.01 | M49: -0.04 | N49: 0.03
C54: Total platform | J54: {=INDEX(J56:J58,S_Scenario)} -> 0.046 | K54: {=INDEX(K56:K58,S_Scenario)} -> 0.15 | L54: {=INDEX(L56:L58,S_Scenario)} -> 0.023 | M54: {=INDEX(M56:M58,S_Scenario)} -> 0.22 | N54: {=INDEX(N56:N58,S_Scenario)} -> 0.05
C56: =C47 -> BULL / BEST CASE | J56: 0.046 | K56: 0.15 | L56: 0.023 | M56: 0.22 | N56: 0.05
C57: =C48 -> BASE CASE | J57: -0.11014254 | K57: 0.1058 | L57: -0.02296982 | M57: 0.2 | N57: 0.04141509
C58: =C49 -> BEAR / WORST CASE | J58: -0.14 | K58: 0.05 | L58: -0.031 | M58: 0.08 | N58: 0.03
C62: Other Business Activities | J62: {=INDEX(J64:J66,S_Scenario)} -> 0.03 | K62: {=INDEX(K64:K66,S_Scenario)} -> 0.09 | L62: {=INDEX(L64:L66,S_Scenario)} -> 0.05 | M62: {=INDEX(M64:M66,S_Scenario)} -> 0.03 | N62: {=INDEX(N64:N66,S_Scenario)} -> 0.05
C64: =C47 -> BULL / BEST CASE | J64: 0.03 | K64: 0.09 | L64: 0.05 | M64: 0.03 | N64: 0.05
C65: =C48 -> BASE CASE | J65: 0.010296157 | K65: 0.07 | L65: 0.0285 | M65: 0.004 | N65: 0.034166667
C66: =C49 -> BEAR / WORST CASE | J66: -0.0079 | K66: 0.05 | L66: -0.012 | M66: -0.022 | N66: 0
C71: Capex | J71: {=INDEX(J73:J75,S_Scenario)} -> 300 | K71: {=INDEX(K73:K75,S_Scenario)} -> 300 | L71: {=INDEX(L73:L75,S_Scenario)} -> 300 | M71: {=INDEX(M73:M75,S_Scenario)} -> 300 | N71: {=INDEX(N73:N75,S_Scenario)} -> 400
C73: =C64 -> BULL / BEST CASE | J73: 300 | K73: 300 | L73: 300 | M73: 300 | N73: 400
C74: =C65 -> BASE CASE | J74: 237 | K74: 245 | L74: 220 | M74: 270 | N74: 300
C75: =C66 -> BEAR / WORST CASE | J75: 200 | K75: 200 | L75: 180 | M75: 200 | N75: 200
C79: Buyback | J79: {=INDEX(J81:J83,S_Scenario)} -> 550 | K79: {=INDEX(K81:K83,S_Scenario)} -> 400 | L79: {=INDEX(L81:L83,S_Scenario)} -> 300 | M79: {=INDEX(M81:M83,S_Scenario)} -> 400 | N79: {=INDEX(N81:N83,S_Scenario)} -> 400
C81: =C73 -> BULL / BEST CASE | J81: 550 | K81: 400 | L81: 300 | M81: 400 | N81: 400
C82: =C74 -> BASE CASE | J82: 500 | K82: 370 | L82: 250 | M82: 350 | N82: 350
C83: =C75 -> BEAR / WORST CASE | J83: 450 | K83: 350 | L83: 200 | M83: 300 | N83: 300

Sheet MODEL&SCHEDULE
C1: FINANCIAL STATEMENTS & SCHEDULES | K1: =SCENARIOS!K1 -> CURRENTLY RUNNING: BULL / BEST CASE
M2: =COVER!B6 -> NEXT PLC
M3: =IF(Balcheck=0, "Bal Check: OK", "ERROR") -> Bal Check: OK
E4: =ASSUMPTIONS!E4 -> 44592 | F4: =ASSUMPTIONS!F4 -> 44957 | G4: =ASSUMPTIONS!G4 -> 45322 | H4: =ASSUMPTIONS!H4 -> 45688 | I4: =ASSUMPTIONS!I4 -> 46053 | J4: =ASSUMPTIONS!J4 -> 46418 | K4: =ASSUMPTIONS!K4 -> 46783 | L4: =ASSUMPTIONS!L4 -> 47149 | ... N4: =ASSUMPTIONS!N4 -> 47879
E5: =ASSUMPTIONS!E5 -> 2022 | F5: =ASSUMPTIONS!F5 -> 2023 | G5: =ASSUMPTIONS!G5 -> 2024 | H5: =ASSUMPTIONS!H5 -> 2025 | I5: =ASSUMPTIONS!I5 -> 2026 | J5: =ASSUMPTIONS!J5 -> 2027 | K5: =ASSUMPTIONS!K5 -> 2028 | L5: =ASSUMPTIONS!L5 -> 2029 | ... N5: =ASSUMPTIONS!N5 -> 2031
B6: ='HISTORICAL FS'!B7 -> Millions for the Year Ended January 31 | C6: INCOME- STATEMENT
C8: ='rough sheet'!C744 -> SEGMENT
C9: ='rough sheet'!C745 -> Online UK | H9: ='rough sheet'!H745 -> 2302.7 | I9: ='rough sheet'!I745 -> 2587.4 | J9: =I9*(1+SCENARIOS!J21) -> 2716.77 | K9: =J9*(1+SCENARIOS!K21) -> 2988.447 | L9: =K9*(1+SCENARIOS!L21) -> 3478.5523 | M9: =L9*(1+SCENARIOS!M21) -> 3895.9786 | N9: =M9*(1+SCENARIOS!N21) -> 4207.6569
C10: ='rough sheet'!C746 -> Online (International) | H10: ='rough sheet'!H746 -> 898.5 | I10: ='rough sheet'!I746 -> 1280.4 | J10: =I10*(1+SCENARIOS!J29) -> 1463.4972 | K10: =J10*(1+SCENARIOS!K29) -> 1683.0218 | L10: =K10*(1+SCENARIOS!L29) -> 1935.475 | M10: =L10*(1+SCENARIOS!M29) -> 2090.3131 | N10: =M10*(1+SCENARIOS!N29) -> 2341.1506
C11: ='rough sheet'!C747 -> Next Online | E11: ='rough sheet'!E747 -> 2863.1 | F11: ='rough sheet'!F747 -> 2743.6 | G11: ='rough sheet'!G747 -> 2901.4 | H11: =SUM(H9:H10) -> 3201.2 | I11: =SUM(I9:I10) -> 3867.8 | J11: =SUM(J9:J10) -> 4180.2672 | K11: =SUM(K9:K10) -> 4671.4688 | L11: =SUM(L9:L10) -> 5414.0274 | M11: =SUM(M9:M10) -> 5986.2916 | N11: =SUM(N9:N10) -> 6548.8075
C12: ='rough sheet'!C748 -> Next Retail | E12: ='rough sheet'!E748 -> 1425.9 | F12: ='rough sheet'!F748 -> 1849.1 | G12: ='rough sheet'!G748 -> 1843.7 | H12: ='rough sheet'!H748 -> 1821.2 | I12: ='rough sheet'!I748 -> 1888 | J12: =I12*(1+SCENARIOS!J45) -> 1906.88 | K12: =J12*(1+SCENARIOS!K45) -> 1964.0864 | L12: =K12*(1+SCENARIOS!L45) -> 2058.3625 | M12: =L12*(1+SCENARIOS!M45) -> 2068.6544 | N12: =M12*(1+SCENARIOS!N45) -> 2213.4602
C13: ='rough sheet'!C749 -> Product Revenue | E13: =E11+E12 -> 4289 | F13: =F11+F12 -> 4592.7 | G13: =G11+G12 -> 4745.1 | H13: =H11+H12 -> 5022.4 | I13: =I11+I12 -> 5755.8 | J13: =J11+J12 -> 6087.1472 | K13: =K11+K12 -> 6635.5552 | L13: =L11+L12 -> 7472.3899 | ... N13: =N11+N12 -> 8762.2677
C14: ='rough sheet'!C750 -> Next Finance/credit account interest | E14: ='rough sheet'!E750 -> 249.4 | F14: ='rough sheet'!F750 -> 274.4 | G14: ='rough sheet'!G750 -> 292.7 | H14: ='rough sheet'!H750 -> 301 | I14: ='rough sheet'!I750 -> 305.7 | J14: =I14*(1+SCENARIOS!J37) -> 311.814 | K14: =J14*(1+SCENARIOS!K37) -> 314.93214 | L14: =K14*(1+SCENARIOS!L37) -> 324.3801 | M14: =L14*(1+SCENARIOS!M37) -> 337.35531 | N14: =M14*(1+SCENARIOS!N37) -> 364.34373
C15: ='rough sheet'!C751 -> Total Platform +next sale of investment | E15: ='rough sheet'!E751 -> 11.3 | F15: ='rough sheet'!F751 -> 75.7 | G15: ='rough sheet'!G751 -> 363.8 | H15: ='rough sheet'!H751 -> 690 | I15: ='rough sheet'!I751 -> 734.3 | J15: =I15*(1+SCENARIOS!J54) -> 768.0778 | K15: =J15*(1+SCENARIOS!K54) -> 883.28947 | L15: =K15*(1+SCENARIOS!L54) -> 903.60513 | M15: =L15*(1+SCENARIOS!M54) -> 1102.3983 | N15: =M15*(1+SCENARIOS!N54) -> 1157.5182
C16: ='rough sheet'!C752 -> Other business Activities | E16: ='rough sheet'!E752 -> 76.2 | F16: ='rough sheet'!F752 -> 91.2 | G16: ='rough sheet'!G752 -> 89.4 | H16: ='rough sheet'!H752 -> 104.7 | I16: ='rough sheet'!I752 -> 105.5 | J16: =I16*(1+SCENARIOS!J62) -> 108.665 | K16: =J16*(1+SCENARIOS!K62) -> 118.44485 | L16: =K16*(1+SCENARIOS!L62) -> 124.36709 | M16: =L16*(1+SCENARIOS!M62) -> 128.09811 | N16: =M16*(1+SCENARIOS!N62) -> 134.50301
C17: ='HISTORICAL FS'!C12 -> Revenue | E17: =E13+E14+E15+E16 -> 4625.9 | F17: =F13+F14+F15+F16 -> 5034 | G17: =G13+G14+G15+G16 -> 5491 | H17: =H13+H14+H15+H16 -> 6118.1 | I17: =I13+I14+I15+I16 -> 6901.3 | J17: =J13+J14+J15+J16 -> 7275.704 | K17: =K13+K14+K15+K16 -> 7952.2216 | L17: =L13+L14+L15+L16 -> 8824.7422 | ... N17: =N13+N14+N15+N16 -> 10418.633
C18: ='HISTORICAL FS'!C13 -> cost of sales | E18: ='HISTORICAL FS'!E13 -> 2625.3 | F18: ='HISTORICAL FS'!F13 -> 2827.7 | G18: ='HISTORICAL FS'!G13 -> 3034.5 | H18: ='HISTORICAL FS'!H13 -> 3456.5 | I18: ='HISTORICAL FS'!I13 -> 3847.5 | J18: =J17*ASSUMPTIONS!$J$55 -> 4080.7103 | K18: =K17*ASSUMPTIONS!$J$55 -> 4460.1475 | L18: =L17*ASSUMPTIONS!$J$55 -> 4949.5164 | M18: =M17*ASSUMPTIONS!$J$55 -> 5397.1203 | N18: =N17*ASSUMPTIONS!$J$55 -> 5843.4787
C19: ='HISTORICAL FS'!C14 -> impairment losses on customer and other receivables | E19: ='HISTORICAL FS'!E14 -> 28.6 | F19: ='HISTORICAL FS'!F14 -> 31 | G19: ='HISTORICAL FS'!G14 -> 36 | H19: ='HISTORICAL FS'!H14 -> 19.4 | I19: ='HISTORICAL FS'!I14 -> 7.1 | J19: 0 | K19: =J19 -> 0 | L19: =K19 -> 0 | M19: =L19 -> 0 | N19: =M19 -> 0
C20: ='HISTORICAL FS'!C15 -> Gross profit/(loss) | E20: =E17-E18-E19 -> 1972 | F20: =F17-F18-F19 -> 2175.3 | G20: =G17-G18-G19 -> 2420.5 | H20: =H17-H18-H19 -> 2642.2 | I20: =I17-I18-I19 -> 3046.7 | J20: =J17-J18-J19 -> 3194.9937 | K20: =K17-K18-K19 -> 3492.0742 | L20: =L17-L18-L19 -> 3875.2258 | ... N20: =N17-N18-N19 -> 4575.1539
C21: ='HISTORICAL FS'!C16 -> Distribution costs | E21: ='HISTORICAL FS'!E16 -> 693.7 | F21: ='HISTORICAL FS'!F16 -> 750 | G21: ='HISTORICAL FS'!G16 -> 794.1 | H21: ='HISTORICAL FS'!H16 -> 878.8 | I21: ='HISTORICAL FS'!I16 -> 1027.1 | J21: =J17*ASSUMPTIONS!$J$57 -> 1071.0298 | K21: =K17*ASSUMPTIONS!$J$57 -> 1170.6175 | L21: =L17*ASSUMPTIONS!$J$57 -> 1299.0581 | M21: =M17*ASSUMPTIONS!$J$57 -> 1416.5369 | N21: =N17*ASSUMPTIONS!$J$57 -> 1533.6889
C22: ='HISTORICAL FS'!C17 -> Administrative expenses | E22: ='HISTORICAL FS'!E17 -> 380.2 | F22: ='HISTORICAL FS'!F17 -> 481.8 | G22: ='HISTORICAL FS'!G17 -> 657.7 | H22: ='HISTORICAL FS'!H17 -> 670.6 | I22: ='HISTORICAL FS'!I17 -> 742.4 | J22: =J17*ASSUMPTIONS!$J$58 -> 749.19312 | K22: =K17*ASSUMPTIONS!$J$58 -> 818.85543 | L22: =L17*ASSUMPTIONS!$J$58 -> 908.70054 | M22: =M17*ASSUMPTIONS!$J$58 -> 990.87783 | N22: =N17*ASSUMPTIONS!$J$58 -> 1072.8265
C23: ='HISTORICAL FS'!C18 -> other losses/Gain-on financial instruments | E23: ='HISTORICAL FS'!E18 -> 2.5 | F23: ='HISTORICAL FS'!F18 -> -16.3 | G23: ='HISTORICAL FS'!G18 -> 12.3 | H23: ='HISTORICAL FS'!H18 -> 3.4 | I23: ='HISTORICAL FS'!I18 -> -3.4 | J23: 0 | K23: 0 | L23: 0 | M23: 0 | N23: 0
C24: ='HISTORICAL FS'!C19 -> Trading profit | E24: =E20-E21-E22+E23 -> 900.6 | F24: =F20-F21-F22+F23 -> 927.2 | G24: =G20-G21-G22+G23 -> 981 | H24: =H20-H21-H22+H23 -> 1096.2 | I24: =I20-I21-I22+I23 -> 1273.8 | J24: =J20-J21-J22+J23 -> 1374.7707 | K24: =K20-K21-K22+K23 -> 1502.6012 | L24: =L20-L21-L22+L23 -> 1667.4671 | ... N24: =N20-N21-N22+N23 -> 1968.6385
C25: ='HISTORICAL FS'!C20 -> share of results of associates and joint ventures | E25: ='HISTORICAL FS'!E20 -> 4.8 | F25: ='HISTORICAL FS'!F20 -> 14.3 | G25: ='HISTORICAL FS'!G20 -> 6.9 | H25: ='HISTORICAL FS'!H20 -> 6.7 | I25: ='HISTORICAL FS'!I20 -> 7.9 | J25: =J389 -> 5.7997423 | K25: =K389 -> 6.7553392 | L25: =L389 -> 7.8683854 | M25: =M389 -> 9.1648232 | N25: =N389 -> 10.674869
C26: ='HISTORICAL FS'!C21 -> Impairment in associates and joint ventures | H26: ='HISTORICAL FS'!H21 -> -13 | I26: ='HISTORICAL FS'!I21 -> -2.9 | J26: =ASSUMPTIONS!J134 -> 0 | K26: =J26 -> 0 | L26: =K26 -> 0 | M26: =L26 -> 0 | N26: =M26 -> 0
C27: ='HISTORICAL FS'!C22 -> Exceptional items- curtailment loss | H27: ='HISTORICAL FS'!H22 -> -14.5 | I27: ='HISTORICAL FS'!I22 -> 0 | J27: =I27 -> 0 | K27: =J27 -> 0 | L27: =K27 -> 0 | M27: =L27 -> 0 | N27: =M27 -> 0
C28: ='HISTORICAL FS'!C23 -> Operating profit/(loss) | E28: =SUM(E24:E27) -> 905.4 | F28: =SUM(F24:F27) -> 941.5 | G28: =SUM(G24:G27) -> 987.9 | H28: =SUM(H24:H27) -> 1075.4 | I28: =SUM(I24:I27) -> 1278.8 | J28: =SUM(J24:J27) -> 1380.5705 | K28: =SUM(K24:K27) -> 1509.3565 | L28: =SUM(L24:L27) -> 1675.3355 | ... N28: =SUM(N24:N27) -> 1979.3134
C29: ='HISTORICAL FS'!C24 -> Gain on Reiss transaction- exceptional items | G29: ='HISTORICAL FS'!G24 -> 108.6 | J29: 0 | K29: =J29 -> 0 | L29: =K29 -> 0 | M29: =L29 -> 0 | N29: =M29 -> 0
C30: ='HISTORICAL FS'!C25 -> Finance income | E30: ='HISTORICAL FS'!E25 -> 4.2 | F30: ='HISTORICAL FS'!F25 -> 5.7 | G30: ='HISTORICAL FS'!G25 -> 6.8 | H30: ='HISTORICAL FS'!H25 -> 8.2 | I30: ='HISTORICAL FS'!I25 -> 11 | J30: =J560 -> 3.6075 | K30: =K560 -> 4.078389 | L30: =L560 -> 8.006496 | M30: =M560 -> 9.1450894 | N30: =N560 -> 20.045055
C31: ='HISTORICAL FS'!C26 -> finance costs | E31: =-'HISTORICAL FS'!E26 -> 86.5 | F31: =-'HISTORICAL FS'!F26 -> 77.9 | G31: =-'HISTORICAL FS'!G26 -> 87.5 | H31: =-'HISTORICAL FS'!H26 -> 96.6 | I31: =-'HISTORICAL FS'!I26 -> 97.2 | J31: =J554 -> -19.459936 | K31: =K554 -> -20.93962 | L31: =L554 -> -28.678782 | M31: =M554 -> -29.824309 | N31: =N554 -> -28.241797
C32: ='HISTORICAL FS'!C27 -> Profit before taxation | E32: =E28+E29+E30-E31 -> 823.1 | F32: =F28+F29+F30-F31 -> 869.3 | G32: =G28+G29+G30-G31 -> 1015.8 | H32: =H28+H29+H30-H31 -> 987 | I32: =I28+I29+I30-I31 -> 1192.6 | J32: =J28+J29+J30-J31 -> 1403.6379 | K32: =K28+K29+K30-K31 -> 1534.3746 | L32: =L28+L29+L30-L31 -> 1712.0208 | ... N32: =N28+N29+N30-N31 -> 2027.6002
C33: ='HISTORICAL FS'!C28 -> Taxation | E33: =-'HISTORICAL FS'!E28 -> 145.6 | F33: =-'HISTORICAL FS'!F28 -> 158.6 | G33: =-'HISTORICAL FS'!G28 -> 215.3 | H33: =-'HISTORICAL FS'!H28 -> 243.8 | I33: =-'HISTORICAL FS'!I28 -> 294.6 | J33: =J428 -> 350.90948 | K33: =K428 -> 383.59364 | L33: =L428 -> 428.0052 | M33: =M428 -> 466.59921 | N33: =N428 -> 506.90006
C34: ='HISTORICAL FS'!C29 -> Net Profit | E34: =E32-E33 -> 677.5 | F34: =F32-F33 -> 710.7 | G34: =G32-G33 -> 800.5 | H34: =H32-H33 -> 743.2 | I34: =I32-I33 -> 898 | J34: =J32-J33 -> 1052.7284 | K34: =K32-K33 -> 1150.7809 | L34: =L32-L33 -> 1284.0156 | ... N34: =N32-N33 -> 1520.7002
C36: ='HISTORICAL FS'!C32 -> Profit attributable to:
C37: ='HISTORICAL FS'!C33 -> Equity holders of the parent company | E37: ='HISTORICAL FS'!E33 -> 677.5 | F37: ='HISTORICAL FS'!F33 -> 711.7 | G37: ='HISTORICAL FS'!G33 -> 802.3 | H37: ='HISTORICAL FS'!H33 -> 736.1 | I37: ='HISTORICAL FS'!I33 -> 888.5 | J37: =J34-J38 -> 1041.4938 | K37: =K34-K38 -> 1137.7566 | L37: =L34-L38 -> 1268.2951 | M37: =M34-M38 -> 1381.7048 | N37: =N34-N38 -> 1500.4139
C38: ='HISTORICAL FS'!C34 -> non controlling interests | E38: ='HISTORICAL FS'!E34 -> 0 | F38: ='HISTORICAL FS'!F34 -> -1 | G38: ='HISTORICAL FS'!G34 -> -1.8 | H38: ='HISTORICAL FS'!H34 -> 7.1 | I38: ='HISTORICAL FS'!I34 -> 9.5 | J38: =J541 -> 11.23463 | K38: =K541 -> 13.024306 | L38: =L541 -> 15.720498 | M38: =M541 -> 18.092806 | N38: =N541 -> 20.286279
E39: =SUM(E37:E38) -> 677.5 | F39: =SUM(F37:F38) -> 710.7 | G39: =SUM(G37:G38) -> 800.5 | H39: =SUM(H37:H38) -> 743.2 | I39: =SUM(I37:I38) -> 898 | J39: =SUM(J37:J38) -> 1052.7284 | K39: =SUM(K37:K38) -> 1150.7809 | L39: =SUM(L37:L38) -> 1284.0156 | ... N39: =SUM(N37:N38) -> 1520.7002
C40: ='HISTORICAL FS'!C36 -> Earnings/(losses) per share
C41: ='HISTORICAL FS'!C37 -> Basic
C42: ='HISTORICAL FS'!C38 -> diluted
C47: Normalisation
C48: =C32 -> Profit before taxation | E48: =E32 -> 823.1 | F48: =F32 -> 869.3 | G48: =G32 -> 1015.8 | H48: =H32 -> 987 | I48: =I32 -> 1192.6 | J48: =J32 -> 1403.6379 | K48: =K32 -> 1534.3746 | L48: =L32 -> 1712.0208 | ... N48: =N32 -> 2027.6002
B49: Adjustments
C50: =C29 -> Gain on Reiss transaction- exceptional items | E50: =E29 -> 0 | F50: =F29 -> 0 | G50: =G29 -> 108.6 | H50: =H29 -> 0 | I50: =I29 -> 0 | J50: =J29 -> 0 | K50: =K29 -> 0 | L50: =L29 -> 0 | ... N50: =N29 -> 0
C51: =C27 -> Exceptional items- curtailment loss | E51: =E27 -> 0 | F51: =F27 -> 0 | G51: =G27 -> 0 | H51: =H27 -> -14.5 | I51: =I27 -> 0 | J51: =J27 -> 0 | K51: =K27 -> 0 | L51: =L27 -> 0 | ... N51: =N27 -> 0
C52: =C26 -> Impairment in associates and joint ventures | E52: =E26 -> 0 | F52: =F26 -> 0 | G52: =G26 -> 0 | H52: =-H26 -> 13 | I52: =-I26 -> 2.9 | J52: =-J26 -> 0 | K52: =-K26 -> 0 | L52: =-L26 -> 0 | M52: =-M26 -> 0 | N52: =-N26 -> 0
C53: =C23 -> other losses/Gain-on financial instruments | E53: =-E23 -> -2.5 | F53: =-F23 -> 16.3 | G53: =-G23 -> -12.3 | H53: =-H23 -> -3.4 | I53: =-I23 -> 3.4 | J53: =-J23 -> 0 | K53: =-K23 -> 0 | L53: =-L23 -> 0 | ... N53: =-N23 -> 0
E54: =SUM(E48:E53) -> 820.6 | F54: =SUM(F48:F53) -> 885.6 | G54: =SUM(G48:G53) -> 1112.1 | H54: =SUM(H48:H53) -> 982.1 | I54: =SUM(I48:I53) -> 1198.9 | J54: =SUM(J48:J53) -> 1403.6379 | K54: =SUM(K48:K53) -> 1534.3746 | L54: =SUM(L48:L53) -> 1712.0208 | ... N54: =SUM(N48:N53) -> 2027.6002
C55: =C807 -> other non -recurring items | E55: =E807 -> -32.7 | F55: =F807 -> -57.9 | G55: =G807 -> -5.1 | H55: =H807 -> 4.5 | I55: =I807 -> -13.1 | J55: 0 | K55: =J55 -> 0 | L55: =K55 -> 0 | M55: =L55 -> 0 | N55: =M55 -> 0
C56: Adjusted Profit Before tax | E56: =SUM(E54:E55) -> 787.9 | F56: =SUM(F54:F55) -> 827.7 | G56: =SUM(G54:G55) -> 1107 | H56: =SUM(H54:H55) -> 986.6 | I56: =SUM(I54:I55) -> 1185.8 | J56: =SUM(J54:J55) -> 1403.6379 | K56: =SUM(K54:K55) -> 1534.3746 | L56: =SUM(L54:L55) -> 1712.0208 | ... N56: =SUM(N54:N55) -> 2027.6002
C59: =C28 -> Operating profit/(loss) | E59: =E28 -> 905.4 | F59: =F28 -> 941.5 | G59: =G28 -> 987.9 | H59: =H28 -> 1075.4 | I59: =I28 -> 1278.8 | J59: =J28 -> 1380.5705 | K59: =K28 -> 1509.3565 | L59: =L28 -> 1675.3355 | ... N59: =N28 -> 1979.3134
C60: =C55 -> other non -recurring items | E60: =E55 -> -32.7 | F60: =F55 -> -57.9 | G60: =G55 -> -5.1 | H60: =H55 -> 4.5 | I60: =I55 -> -13.1 | J60: =J55 -> 0 | K60: =K55 -> 0 | L60: =L55 -> 0 | ... N60: =N55 -> 0
C61: =C51 -> Exceptional items- curtailment loss | E61: =E51 -> 0 | F61: =F51 -> 0 | G61: =G51 -> 0 | H61: =H51 -> -14.5 | I61: =I51 -> 0 | J61: =J51 -> 0 | K61: =K51 -> 0 | L61: =L51 -> 0 | ... N61: =N51 -> 0
C62: =C52 -> Impairment in associates and joint ventures | E62: =E52 -> 0 | F62: =F52 -> 0 | G62: =G52 -> 0 | H62: =H52 -> 13 | I62: =I52 -> 2.9 | J62: =J52 -> 0 | K62: =K52 -> 0 | L62: =L52 -> 0 | ... N62: =N52 -> 0
C63: =C53 -> other losses/Gain-on financial instruments | E63: =E53 -> -2.5 | F63: =F53 -> 16.3 | G63: =G53 -> -12.3 | H63: =H53 -> -3.4 | I63: =I53 -> 3.4 | J63: =J53 -> 0 | K63: =K53 -> 0 | L63: =L53 -> 0 | ... N63: =N53 -> 0
C64: EBIT | E64: =SUM(E59:E63) -> 870.2 | F64: =SUM(F59:F63) -> 899.9 | G64: =SUM(G59:G63) -> 970.5 | H64: =SUM(H59:H63) -> 1075 | I64: =SUM(I59:I63) -> 1272 | J64: =SUM(J59:J63) -> 1380.5705 | K64: =SUM(K59:K63) -> 1509.3565 | L64: =SUM(L59:L63) -> 1675.3355 | ... N64: =SUM(N59:N63) -> 1979.3134
C66: Depreciation and Amortisation | E66: =E810+E811 -> 220.6 | F66: =F810+F811 -> 219.6 | G66: =G810+G811 -> 240.6 | H66: =H810+H811 -> 288.9 | I66: =I810+I811 -> 302.5 | J66: =J96+J97+J98 -> 307.61188 | K66: =K96+K97+K98 -> 325.6816 | L66: =L96+L97+L98 -> 342.50128 | M66: =M96+M97+M98 -> 358.69839 | N66: =N96+N97+N98 -> 374.13674
C67: EBITDA | E67: =E64+E66 -> 1090.8 | F67: =F64+F66 -> 1119.5 | G67: =G64+G66 -> 1211.1 | H67: =H64+H66 -> 1363.9 | I67: =I64+I66 -> 1574.5 | J67: =J64+J66 -> 1688.1824 | K67: =K64+K66 -> 1835.0381 | L67: =L64+L66 -> 2017.8368 | ... N67: =N64+N66 -> 2353.4501
C70: Adjusted Tax | E70: =G816 -> 136.8 | F70: =J816 -> 148.2 | G70: =M816 -> 238.1 | H70: =P816 -> 243.7 | I70: =S816 -> 292.9 | J70: =J33 -> 350.90948 | K70: =K33 -> 383.59364 | L70: =L33 -> 428.0052 | M70: =M33 -> 466.59921 | N70: =N33 -> 506.90006
C71: Recurring Net Income | E71: =E56-E70 -> 651.1 | F71: =F56-F70 -> 679.5 | G71: =G56-G70 -> 868.9 | H71: =H56-H70 -> 742.9 | I71: =I56-I70 -> 892.9 | J71: =J56-J70 -> 1052.7284 | K71: =K56-K70 -> 1150.7809 | L71: =L56-L70 -> 1284.0156 | ... N71: =N56-N70 -> 1520.7002
C73: EBIAT/NOPAT | E73: =E64-(E64*$J$420) -> 652.65 | F73: =F64-(F64*$J$420) -> 674.925 | G73: =G64-(G64*$J$420) -> 727.875 | H73: =H64-(H64*$J$420) -> 806.25 | I73: =I64-(I64*$J$420) -> 954 | J73: =J64-(J64*$J$420) -> 1035.4279 | K73: =K64-(K64*$J$420) -> 1132.0174 | L73: =L64-(L64*$J$420) -> 1256.5016 | ... N73: =N64-(N64*$J$420) -> 1484.485
C77: EBIT margin | D77: % | E77: =E64/E17 -> 0.18811475 | F77: =F64/F17 -> 0.1787644 | G77: =G64/G17 -> 0.17674376 | H77: =H64/H17 -> 0.17570814 | I77: =I64/I17 -> 0.1843131 | J77: =J64/J17 -> 0.18975078 | K77: =K64/K17 -> 0.18980313 | L77: =L64/L17 -> 0.18984527 | ... N77: =N64/N17 -> 0.18997823
C78: EBITDA margin | D78: % | E78: =E67/E17 -> 0.23580276 | F78: =F67/F17 -> 0.22238776 | G78: =G67/G17 -> 0.22056092 | H78: =H67/H17 -> 0.22292869 | I78: =I67/I17 -> 0.22814542 | J78: =J67/J17 -> 0.2320301 | K78: =K67/K17 -> 0.23075792 | L78: =L67/L17 -> 0.22865674 | ... N78: =N67/N17 -> 0.22588858
C79: EBIAT/NOPAT margin | D79: % | E79: =E73/E17 -> 0.14108606 | F79: =F73/F17 -> 0.1340733 | G79: =G73/G17 -> 0.13255782 | H79: =H73/H17 -> 0.13178111 | I79: =I73/I17 -> 0.13823483 | J79: =J73/J17 -> 0.14231308 | K79: =K73/K17 -> 0.14235235 | L79: =L73/L17 -> 0.14238395 | ... N79: =N73/N17 -> 0.14248367
C80: Recurring NI margin | D80: % | E80: =E71/E17 -> 0.14075099 | F80: =F71/F17 -> 0.13498212 | G80: =G71/G17 -> 0.15824076 | H80: =H71/H17 -> 0.12142659 | I80: =I71/I17 -> 0.12938142 | J80: =J71/J17 -> 0.14469094 | K80: =K71/K17 -> 0.14471188 | L80: =L71/L17 -> 0.14550177 | ... N80: =N71/N17 -> 0.14595967
C81: Return on Asset | D81: % | F81: =F71/AVERAGE(E205:F205) -> 0.17060862 | G81: =G71/AVERAGE(F205:G205) -> 0.19956133 | H81: =H71/AVERAGE(G205:H205) -> 0.15482244 | I81: =I71/AVERAGE(H205:I205) -> 0.18245162 | J81: =J71/AVERAGE(I205:J205) -> 0.20969811 | K81: =K71/AVERAGE(J205:K205) -> 0.21534797 | L81: =L71/AVERAGE(K205:L205) -> 0.22253395 | M81: =M71/AVERAGE(L205:M205) -> 0.22022447 | N81: =N71/AVERAGE(M205:N205) -> 0.2147232
C82: Return on Equity | D82: % | F82: =F71/AVERAGE(E232:F232) -> 0.62479886 | G82: =G71/AVERAGE(F232:G232) -> 0.61977959 | H82: =H71/AVERAGE(G232:H232) -> 0.43788866 | I82: =I71/AVERAGE(H232:I232) -> 0.50520539 | J82: =J71/AVERAGE(I232:J232) -> 0.54067219 | K82: =K71/AVERAGE(J232:K232) -> 0.50579958 | L82: =L71/AVERAGE(K232:L232) -> 0.47686312 | M82: =M71/AVERAGE(L232:M232) -> 0.43835069 | N82: =N71/AVERAGE(M232:N232) -> 0.40841995
B83: Dupont Analysis
C84: =C80 -> Recurring NI margin | D84: % | F84: =F80 -> 0.13498212 | G84: =G80 -> 0.15824076 | H84: =H80 -> 0.12142659 | I84: =I80 -> 0.12938142 | J84: =J80 -> 0.14469094 | K84: =K80 -> 0.14471188 | L84: =L80 -> 0.14550177 | M84: =M80 -> 0.14546681 | N84: =N80 -> 0.14595967
C85: Asset Turnover | D85: Multiple | F85: =F17/((E205+F205)/2) -> 1.2639349 | G85: =G17/((F205+G205)/2) -> 1.2611247 | H85: =H17/((G205+H205)/2) -> 1.2750292 | I85: =I17/((H205+I205)/2) -> 1.4101841 | J85: =J17/((I205+J205)/2) -> 1.4492829 | K85: =K17/((J205+K205)/2) -> 1.4881154 | L85: =L17/((K205+L205)/2) -> 1.5294244 | M85: =M17/((L205+M205)/2) -> 1.5139156 | N85: =N17/((M205+N205)/2) -> 1.4711132
C86: Financial leverage | D86: Multiple | F86: =AVERAGE(E205:F205)/AVERAGE(E232:F232) -> 3.6621765 | G86: =AVERAGE(F205:G205)/AVERAGE(F232:G232) -> 3.1057099 | H86: =AVERAGE(G205:H205)/AVERAGE(G232:H232) -> 2.8283281 | I86: =AVERAGE(H205:I205)/AVERAGE(H232:I232) -> 2.7689827 | J86: =AVERAGE(I205:J205)/AVERAGE(I232:J232) -> 2.5783361 | K86: =AVERAGE(J205:K205)/AVERAGE(J232:K232) -> 2.3487548 | L86: =AVERAGE(K205:L205)/AVERAGE(K232:L232) -> 2.142878 | M86: =AVERAGE(L205:M205)/AVERAGE(L232:M232) -> 1.9904722 | N86: =AVERAGE(M205:N205)/AVERAGE(M232:N232) -> 1.9020765
C87: Return on Equity | D87: % | F87: =F84*F85*F86 -> 0.62479886 | G87: =G84*G85*G86 -> 0.61977959 | H87: =H84*H85*H86 -> 0.43788866 | I87: =I84*I85*I86 -> 0.50520539 | J87: =J84*J85*J86 -> 0.54067219 | K87: =K84*K85*K86 -> 0.50579958 | L87: =L84*L85*L86 -> 0.47686312 | M87: =M84*M85*M86 -> 0.43835069 | N87: =N84*N85*N86 -> 0.40841995
C89: Cost of Sales as a % of revenue | E89: =E18/E17 -> 0.567522 | F89: =F18/F17 -> 0.5617203 | G89: =G18/G17 -> 0.55263158 | H89: =H18/H17 -> 0.56496298 | I89: =I18/I17 -> 0.55750366 | J89: =J18/J17 -> 0.5608681 | K89: =K18/K17 -> 0.5608681 | L89: =L18/L17 -> 0.5608681 | ... N89: =N18/N17 -> 0.5608681
C91: ='HISTORICAL FS'!C46 -> CASH-FLOW
C93: ='rough sheet'!C872 -> Operating profit | E93: ='rough sheet'!E872 -> 905.4 | F93: ='rough sheet'!F872 -> 941.5 | G93: ='rough sheet'!G872 -> 987.9 | H93: ='rough sheet'!H872 -> 1075.4 | I93: ='rough sheet'!I872 -> 1278.8 | J93: =J28 -> 1380.5705 | K93: =K28 -> 1509.3565 | L93: =L28 -> 1675.3355 | M93: =M28 -> 1827.4274 | N93: =N28 -> 1979.3134
C94: ='rough sheet'!C873 -> Profit on disposal of associate | E94: ='rough sheet'!E873 -> 0 | F94: ='rough sheet'!F873 -> 0 | G94: ='rough sheet'!G873 -> 0 | H94: ='rough sheet'!H873 -> 0 | I94: ='rough sheet'!I873 -> -16.3 | J94: 0 | K94: =J94 -> 0 | L94: =K94 -> 0 | M94: =L94 -> 0 | N94: =M94 -> 0
C96: ='rough sheet'!C875 -> Depreciation, impairment and (profit)/loss on disposal of property, plant and equipment | E96: ='rough sheet'!E875 -> 90.3 | F96: ='rough sheet'!F875 -> 80.6 | G96: ='rough sheet'!G875 -> 95.7 | H96: ='rough sheet'!H875 -> 117.9 | I96: ='rough sheet'!I875 -> 119.2 | J96: =J367 -> 108.68145 | K96: =K367 -> 131.18843 | L96: =L367 -> 150.03195 | M96: =M367 -> 165.80831 | N96: =N367 -> 179.01675
C97: ='rough sheet'!C876 -> Depreciation and impairment on right-of-use assets | E97: ='rough sheet'!E876 -> 112.6 | F97: ='rough sheet'!F876 -> 72.7 | G97: ='rough sheet'!G876 -> 111.8 | H97: ='rough sheet'!H876 -> 137.9 | I97: ='rough sheet'!I876 -> 156.4 | J97: =J376 -> 137.7241 | K97: =K376 -> 133.98686 | L97: =L376 -> 132.60301 | M97: =M376 -> 133.60885 | N97: =N376 -> 136.37369
C98: ='rough sheet'!C877 -> Amortisation and impairment of intangible assets | E98: ='rough sheet'!E877 -> 4.3 | F98: ='rough sheet'!F877 -> 12.5 | G98: ='rough sheet'!G877 -> 38.5 | H98: ='rough sheet'!H877 -> 55.2 | I98: ='rough sheet'!I877 -> 59.1 | J98: =J383 -> 61.206333 | K98: =K383 -> 60.506314 | L98: =L383 -> 59.866329 | M98: =M383 -> 59.281228 | N98: =N383 -> 58.746305
C99: ='rough sheet'!C878 -> Amortisation, impairemnt & disposals of investments | E99: ='rough sheet'!E878 -> 0 | F99: ='rough sheet'!F878 -> 1.1 | G99: ='rough sheet'!G878 -> 0.8 | H99: ='rough sheet'!H878 -> 13.5 | I99: ='rough sheet'!I878 -> 5.6 | J99: 0 | K99: =J99 -> 0 | L99: =K99 -> 0 | M99: =L99 -> 0 | N99: =M99 -> 0
C100: ='rough sheet'!C879 -> Share option charge | E100: ='rough sheet'!E879 -> 19.9 | F100: ='rough sheet'!F879 -> 24.3 | G100: ='rough sheet'!G879 -> 31.9 | H100: ='rough sheet'!H879 -> 40.9 | I100: ='rough sheet'!I879 -> 43.1 | J100: =I100*(1+ASSUMPTIONS!$J$68) -> 45.418337 | K100: =J100*(1+ASSUMPTIONS!$J$68) -> 47.861378 | L100: =K100*(1+ASSUMPTIONS!$J$68) -> 50.435828 | M100: =L100*(1+ASSUMPTIONS!$J$68) -> 53.148758 | N100: =M100*(1+ASSUMPTIONS!$J$68) -> 56.007615
C102: ='rough sheet'!C880 -> Share of profit of associates and joint ventures | E102: ='rough sheet'!E880 -> -4.8 | F102: ='rough sheet'!F880 -> -14.3 | G102: ='rough sheet'!G880 -> -6.9 | H102: ='rough sheet'!H880 -> -6.7 | I102: ='rough sheet'!I880 -> -7.9 | J102: =-J25 -> -5.7997423 | K102: =-K25 -> -6.7553392 | L102: =-L25 -> -7.8683854 | M102: =-M25 -> -9.1648232 | N102: =-N25 -> -10.674869
C103: ='rough sheet'!C881 -> Exchange movement | E103: ='rough sheet'!E881 -> -1.6 | F103: ='rough sheet'!F881 -> -0.8 | G103: ='rough sheet'!G881 -> -15.5 | H103: ='rough sheet'!H881 -> -5.6 | I103: ='rough sheet'!I881 -> 5.5 | J103: 0 | K103: =J103 -> 0 | L103: =K103 -> 0 | M103: =L103 -> 0 | N103: =M103 -> 0
C104: ='rough sheet'!C882 -> Net pension contributions less income statement charge | E104: ='rough sheet'!E882 -> -2.7 | F104: ='rough sheet'!F882 -> 0 | G104: ='rough sheet'!G882 -> 0 | H104: ='rough sheet'!H882 -> 0 | I104: ='rough sheet'!I882 -> 0 | J104: =I104 -> 0 | K104: =J104 -> 0 | L104: =K104 -> 0 | M104: =L104 -> 0 | N104: =M104 -> 0
C105: (Increase)/decrease in provisions | J105: =J736+J737+J739 -> 5.1067974 | K105: =K736+K737+K739 -> 5.2034161 | L105: =L736+L737+L739 -> 5.3018627 | M105: =M736+M737+M739 -> 5.4021719 | N105: =N736+N737+N739 -> 5.5043789
C106: ='rough sheet'!C884 -> Increase in inventories and right of return asset | E106: ='rough sheet'!E884 -> -96.5 | F106: ='rough sheet'!F884 -> -22.8 | G106: ='rough sheet'!G884 -> 15.3 | H106: ='rough sheet'!H884 -> -100.3 | I106: ='rough sheet'!I884 -> -79.2 | J106: =(I261+I263)-(J261+J263) -> -178.11217 | K106: =(J261+J263)-(K261+K263) -> -59.363435 | L106: =(K261+K263)-(L261+L263) -> -56.504239 | M106: =(L261+L263)-(M261+M263) -> -155.30845 | N106: =(M261+M263)-(N261+N263) -> -96.703765
C107: ='rough sheet'!C885 -> (Increase)/decrease in customer and other receivables | E107: ='rough sheet'!E885 -> -165.4 | F107: ='rough sheet'!F885 -> -156.5 | G107: ='rough sheet'!G885 -> 3.7 | H107: ='rough sheet'!H885 -> -52.3 | I107: ='rough sheet'!I885 -> -153.7 | J107: =I262-J262 -> 96.868872 | K107: =J262-K262 -> -165.59563 | L107: =K262-L262 -> -224.71712 | M107: =L262-M262 -> -212.83533 | N107: =M262-N262 -> -174.53644
C108: ='rough sheet'!C886 -> Increase/(decrease) in trade and other payables | E108: ='rough sheet'!E886 -> 235.2 | F108: ='rough sheet'!F886 -> 12 | G108: ='rough sheet'!G886 -> 47.6 | H108: ='rough sheet'!H886 -> 93.2 | I108: ='rough sheet'!I886 -> 45.9 | J108: =-(I267-J267) -> 124.14811 | K108: =-(J267-K267) -> 125.48647 | L108: =-(K267-L267) -> 130.57495 | M108: =-(L267-M267) -> 174.67431 | N108: =-(M267-N267) -> 6.7796191
C109: Change in working capital
C110: ='rough sheet'!C887 -> Cash flow from Operations | E110: =SUM(E93:E108) -> 1096.7 | F110: =SUM(F93:F108) -> 950.3 | G110: =SUM(G93:G108) -> 1310.8 | H110: =SUM(H93:H108) -> 1369.1 | I110: =SUM(I93:I108) -> 1456.5 | J110: =SUM(J93:J108) -> 1775.8126 | K110: =SUM(K93:K108) -> 1781.875 | L110: =SUM(L93:L108) -> 1915.0597 | ... N110: =SUM(N93:N108) -> 2139.8267
C111: ='rough sheet'!C888 -> corporation tax paid | E111: ='rough sheet'!E888 -> -125.3 | F111: ='rough sheet'!F888 -> -151.5 | G111: ='rough sheet'!G888 -> -193.3 | H111: ='rough sheet'!H888 -> -242.6 | I111: ='rough sheet'!I888 -> -233.1 | J111: =-J430 -> -265 | K111: =-K430 -> -365.09504 | L111: =-L430 -> -407.36487 | M111: =-M430 -> -444.09771 | N111: =-N430 -> -482.45507
C113: ='rough sheet'!C889 -> Net cash from Operating activities | E113: =E110+E111 -> 971.4 | F113: =F110+F111 -> 798.8 | G113: =G110+G111 -> 1117.5 | H113: =H110+H111 -> 1126.5 | I113: =I110+I111 -> 1223.4 | J113: =J110+J111 -> 1510.8126 | K113: =K110+K111 -> 1416.78 | L113: =L110+L111 -> 1507.6948 | ... N113: =N110+N111 -> 1657.3716
C115: ='rough sheet'!C891 -> Cashflow from Investing activities
C117: ='rough sheet'!C893 -> Additions to PPE | E117: ='rough sheet'!E893 -> -239.2 | F117: ='rough sheet'!F893 -> -207.1 | G117: ='rough sheet'!G893 -> -160.9 | H117: ='rough sheet'!H893 -> -122.9 | I117: ='rough sheet'!I893 -> -139.6 | J117: =-J366 -> -246.95627 | K117: =-K366 -> -246.95627 | L117: =-L366 -> -246.95627 | M117: =-M366 -> -246.95627 | N117: =-N366 -> -329.27503
C118: ='rough sheet'!C894 -> Movements in Capital accruals | E118: ='rough sheet'!E894 -> -4.4 | F118: ='rough sheet'!F894 -> 2 | G118: ='rough sheet'!G894 -> 23.9 | H118: ='rough sheet'!H894 -> -6.4 | I118: ='rough sheet'!I894 -> 4.2 | J118: 0 | K118: =J118 -> 0 | L118: =K118 -> 0 | M118: =L118 -> 0 | N118: =M118 -> 0
C119: ='rough sheet'!C895 -> Payments to acquire PPE | E119: =E117+E118 -> -243.6 | F119: =F117+F118 -> -205.1 | G119: =G117+G118 -> -137 | H119: =H117+H118 -> -129.3 | I119: =I117+I118 -> -135.4 | J119: =J117+J118 -> -246.95627 | K119: =K117+K118 -> -246.95627 | L119: =L117+L118 -> -246.95627 | ... N119: =N117+N118 -> -329.27503
C120: ='rough sheet'!C896 -> purchase of intangible assets | E120: ='rough sheet'!E896 -> -22.7 | F120: ='rough sheet'!F896 -> -41 | G120: ='rough sheet'!G896 -> -51.2 | H120: ='rough sheet'!H896 -> -28.2 | I120: ='rough sheet'!I896 -> -35.8 | J120: =-J382 -> -53.043725 | K120: =-K382 -> -53.043725 | L120: =-L382 -> -53.043725 | M120: =-M382 -> -53.043725 | N120: =-N382 -> -70.724967
C121: ='rough sheet'!C897 -> Total Capital expenditure | E121: =E119+E120 -> -266.3 | F121: =F119+F120 -> -246.1 | G121: =G119+G120 -> -188.2 | H121: =H119+H120 -> -157.5 | I121: =I119+I120 -> -171.2 | J121: =J119+J120 -> -300 | K121: =K119+K120 -> -300 | L121: =L119+L120 -> -300 | ... N121: =N119+N120 -> -400
C123: ='rough sheet'!C899 -> Proceeds from sale of held for sale assets | E123: ='rough sheet'!E899 -> 15.5 | F123: ='rough sheet'!F899 -> 41.7 | G123: ='rough sheet'!G899 -> 3.3 | H123: ='rough sheet'!H899 -> 0 | I123: ='rough sheet'!I899 -> 55.7 | J123: 0 | K123: =J123 -> 0 | L123: =K123 -> 0 | M123: =L123 -> 0 | N123: =M123 -> 0
C124: ='rough sheet'!C900 -> Proceeds from sale of PPE | E124: ='rough sheet'!E900 -> 3.4 | F124: ='rough sheet'!F900 -> 0 | G124: ='rough sheet'!G900 -> 2 | H124: ='rough sheet'!H900 -> 2.6 | I124: ='rough sheet'!I900 -> 0.4 | J124: 0 | K124: =J124 -> 0 | L124: =K124 -> 0 | M124: =L124 -> 0 | N124: =M124 -> 0
...

Sheet SENSITIVITY
C1: SENSITIVITY ANALYSIS | K1: ='MODEL&SCHEDULE'!K1 -> CURRENTLY RUNNING: BULL / BEST CASE
C2: TORNADO CHART, ONE WAY & 2 WAY | M2: ='MODEL&SCHEDULE'!M2 -> NEXT PLC
M3: ='MODEL&SCHEDULE'!M3 -> Bal Check: OK
J4: ='MODEL&SCHEDULE'!J4 -> 46418 | K4: ='MODEL&SCHEDULE'!K4 -> 46783 | L4: ='MODEL&SCHEDULE'!L4 -> 47149 | M4: ='MODEL&SCHEDULE'!M4 -> 47514 | N4: ='MODEL&SCHEDULE'!N4 -> 47879
J5: ='MODEL&SCHEDULE'!J5 -> 2027 | K5: ='MODEL&SCHEDULE'!K5 -> 2028 | L5: ='MODEL&SCHEDULE'!L5 -> 2029 | M5: ='MODEL&SCHEDULE'!M5 -> 2030 | N5: ='MODEL&SCHEDULE'!N5 -> 2031
C7: Tornado Chart | I7: One-way Analysis | Q7: Two-way Analysis
D8: =R8 -> 2027 ONLY using the Whole Revenue | J8: ACROSS ALL YEARS | R8: 2027 ONLY using the Whole Revenue
U9: =L10 -> EBIAT/NOPAT
L10: =C92 -> EBIAT/NOPAT | Q10: Online UK Revenue Growth | T10: EBIT margin
I11: Online UK Revenue Growth | Q11: =I96*(1+J97)*(J88*(1-J90)) -> 1035.4279 | R11: 0.175 | S11: 0.18 | T11: 0.185 | U11: 0.18980011 | V11: 0.19 | W11: 0.195 | X11: 0.2
I12: 0.03 | J12: =('MODEL&SCHEDULE'!J$17-SENSITIVITY!I$85*SENSITIVITY!J$87+SENSITIVITY!I$85*SENSITIVITY!$I12)*(SENSITIVITY!J$88*(1-SENSITIVITY!$J$90)) -> 1028.0634 | K12: =('MODEL&SCHEDULE'!K$17-SENSITIVITY!J$85*SENSITIVITY!K$87+SENSITIVITY!J$85*SENSITIVITY!$I12)*(SENSITIVITY!K$88*(1-SENSITIVITY!$J$90)) -> 1104.9457 | L12: =('MODEL&SCHEDULE'!L$17-SENSITIVITY!K$85*SENSITIVITY!L$87+SENSITIVITY!K$85*SENSITIVITY!$I12)*(SENSITIVITY!L$88*(1-SENSITIVITY!$J$90)) -> 1199.4837 | M12: =('MODEL&SCHEDULE'!M$17-SENSITIVITY!L$85*SENSITIVITY!M$87+SENSITIVITY!L$85*SENSITIVITY!$I12)*(SENSITIVITY!M$88*(1-SENSITIVITY!$J$90)) -> 1325.9802 | N12: =('MODEL&SCHEDULE'!N$17-SENSITIVITY!M$85*SENSITIVITY!N$87+SENSITIVITY!M$85*SENSITIVITY!$I12)*(SENSITIVITY!N$88*(1-SENSITIVITY!$J$90)) -> 1456.7294 | Q12: -0.02 | R12: 887.67971 | S12: 913.04199 | T12: 938.40427 | U12: 962.75259 | V12: 963.76655 | W12: 989.12882 | X12: 1014.4911
I13: 0.04 | J13: =('MODEL&SCHEDULE'!J$17-SENSITIVITY!I$85*SENSITIVITY!J$87+SENSITIVITY!I$85*SENSITIVITY!$I13)*(SENSITIVITY!J$88*(1-SENSITIVITY!$J$90)) -> 1031.7457 | K13: =('MODEL&SCHEDULE'!K$17-SENSITIVITY!J$85*SENSITIVITY!K$87+SENSITIVITY!J$85*SENSITIVITY!$I13)*(SENSITIVITY!K$88*(1-SENSITIVITY!$J$90)) -> 1108.8131 | L13: =('MODEL&SCHEDULE'!L$17-SENSITIVITY!K$85*SENSITIVITY!L$87+SENSITIVITY!K$85*SENSITIVITY!$I13)*(SENSITIVITY!L$88*(1-SENSITIVITY!$J$90)) -> 1203.7388 | M13: =('MODEL&SCHEDULE'!M$17-SENSITIVITY!L$85*SENSITIVITY!M$87+SENSITIVITY!L$85*SENSITIVITY!$I13)*(SENSITIVITY!M$88*(1-SENSITIVITY!$J$90)) -> 1330.9347 | N13: =('MODEL&SCHEDULE'!N$17-SENSITIVITY!M$85*SENSITIVITY!N$87+SENSITIVITY!M$85*SENSITIVITY!$I13)*(SENSITIVITY!N$88*(1-SENSITIVITY!$J$90)) -> 1462.2805 | Q13: -0.01 | R13: 896.73767 | S13: 922.35875 | T13: 947.97982 | U13: 972.5766 | V13: 973.6009 | W13: 999.22197 | X13: 1024.8431
I14: 0.05 | J14: =('MODEL&SCHEDULE'!J$17-SENSITIVITY!I$85*SENSITIVITY!J$87+SENSITIVITY!I$85*SENSITIVITY!$I14)*(SENSITIVITY!J$88*(1-SENSITIVITY!$J$90)) -> 1035.4279 | K14: =('MODEL&SCHEDULE'!K$17-SENSITIVITY!J$85*SENSITIVITY!K$87+SENSITIVITY!J$85*SENSITIVITY!$I14)*(SENSITIVITY!K$88*(1-SENSITIVITY!$J$90)) -> 1112.6805 | L14: =('MODEL&SCHEDULE'!L$17-SENSITIVITY!K$85*SENSITIVITY!L$87+SENSITIVITY!K$85*SENSITIVITY!$I14)*(SENSITIVITY!L$88*(1-SENSITIVITY!$J$90)) -> 1207.9939 | M14: =('MODEL&SCHEDULE'!M$17-SENSITIVITY!L$85*SENSITIVITY!M$87+SENSITIVITY!L$85*SENSITIVITY!$I14)*(SENSITIVITY!M$88*(1-SENSITIVITY!$J$90)) -> 1335.8892 | N14: =('MODEL&SCHEDULE'!N$17-SENSITIVITY!M$85*SENSITIVITY!N$87+SENSITIVITY!M$85*SENSITIVITY!$I14)*(SENSITIVITY!N$88*(1-SENSITIVITY!$J$90)) -> 1467.8316 | Q14: 0 | R14: 905.79562 | S14: 931.6755 | T14: 957.55537 | U14: 982.40061 | V14: 983.43525 | W14: 1009.3151 | X14: 1035.195
I15: 0.06 | J15: =('MODEL&SCHEDULE'!J$17-SENSITIVITY!I$85*SENSITIVITY!J$87+SENSITIVITY!I$85*SENSITIVITY!$I15)*(SENSITIVITY!J$88*(1-SENSITIVITY!$J$90)) -> 1039.1101 | K15: =('MODEL&SCHEDULE'!K$17-SENSITIVITY!J$85*SENSITIVITY!K$87+SENSITIVITY!J$85*SENSITIVITY!$I15)*(SENSITIVITY!K$88*(1-SENSITIVITY!$J$90)) -> 1116.5479 | L15: =('MODEL&SCHEDULE'!L$17-SENSITIVITY!K$85*SENSITIVITY!L$87+SENSITIVITY!K$85*SENSITIVITY!$I15)*(SENSITIVITY!L$88*(1-SENSITIVITY!$J$90)) -> 1212.2489 | M15: =('MODEL&SCHEDULE'!M$17-SENSITIVITY!L$85*SENSITIVITY!M$87+SENSITIVITY!L$85*SENSITIVITY!$I15)*(SENSITIVITY!M$88*(1-SENSITIVITY!$J$90)) -> 1340.8437 | N15: =('MODEL&SCHEDULE'!N$17-SENSITIVITY!M$85*SENSITIVITY!N$87+SENSITIVITY!M$85*SENSITIVITY!$I15)*(SENSITIVITY!N$88*(1-SENSITIVITY!$J$90)) -> 1473.3828 | Q15: 0.01 | R15: 914.85358 | S15: 940.99226 | T15: 967.13093 | U15: 992.22461 | V15: 993.2696 | W15: 1019.4083 | X15: 1045.547
I16: 0.07 | J16: =('MODEL&SCHEDULE'!J$17-SENSITIVITY!I$85*SENSITIVITY!J$87+SENSITIVITY!I$85*SENSITIVITY!$I16)*(SENSITIVITY!J$88*(1-SENSITIVITY!$J$90)) -> 1042.7923 | K16: =('MODEL&SCHEDULE'!K$17-SENSITIVITY!J$85*SENSITIVITY!K$87+SENSITIVITY!J$85*SENSITIVITY!$I16)*(SENSITIVITY!K$88*(1-SENSITIVITY!$J$90)) -> 1120.4153 | L16: =('MODEL&SCHEDULE'!L$17-SENSITIVITY!K$85*SENSITIVITY!L$87+SENSITIVITY!K$85*SENSITIVITY!$I16)*(SENSITIVITY!L$88*(1-SENSITIVITY!$J$90)) -> 1216.504 | M16: =('MODEL&SCHEDULE'!M$17-SENSITIVITY!L$85*SENSITIVITY!M$87+SENSITIVITY!L$85*SENSITIVITY!$I16)*(SENSITIVITY!M$88*(1-SENSITIVITY!$J$90)) -> 1345.7982 | N16: =('MODEL&SCHEDULE'!N$17-SENSITIVITY!M$85*SENSITIVITY!N$87+SENSITIVITY!M$85*SENSITIVITY!$I16)*(SENSITIVITY!N$88*(1-SENSITIVITY!$J$90)) -> 1478.9339 | Q16: 0.02 | R16: 923.91154 | S16: 950.30901 | T16: 976.70648 | U16: 1002.0486 | V16: 1003.104 | W16: 1029.5014 | X16: 1055.8989
I17: 0.08 | J17: =('MODEL&SCHEDULE'!J$17-SENSITIVITY!I$85*SENSITIVITY!J$87+SENSITIVITY!I$85*SENSITIVITY!$I17)*(SENSITIVITY!J$88*(1-SENSITIVITY!$J$90)) -> 1046.4745 | K17: =('MODEL&SCHEDULE'!K$17-SENSITIVITY!J$85*SENSITIVITY!K$87+SENSITIVITY!J$85*SENSITIVITY!$I17)*(SENSITIVITY!K$88*(1-SENSITIVITY!$J$90)) -> 1124.2826 | L17: =('MODEL&SCHEDULE'!L$17-SENSITIVITY!K$85*SENSITIVITY!L$87+SENSITIVITY!K$85*SENSITIVITY!$I17)*(SENSITIVITY!L$88*(1-SENSITIVITY!$J$90)) -> 1220.7591 | M17: =('MODEL&SCHEDULE'!M$17-SENSITIVITY!L$85*SENSITIVITY!M$87+SENSITIVITY!L$85*SENSITIVITY!$I17)*(SENSITIVITY!M$88*(1-SENSITIVITY!$J$90)) -> 1350.7526 | N17: =('MODEL&SCHEDULE'!N$17-SENSITIVITY!M$85*SENSITIVITY!N$87+SENSITIVITY!M$85*SENSITIVITY!$I17)*(SENSITIVITY!N$88*(1-SENSITIVITY!$J$90)) -> 1484.485 | Q17: 0.03 | R17: 932.96949 | S17: 959.62577 | T17: 986.28204 | U17: 1011.8726 | V17: 1012.9383 | W17: 1039.5946 | X17: 1066.2509
I18: 0.09 | J18: =('MODEL&SCHEDULE'!J$17-SENSITIVITY!I$85*SENSITIVITY!J$87+SENSITIVITY!I$85*SENSITIVITY!$I18)*(SENSITIVITY!J$88*(1-SENSITIVITY!$J$90)) -> 1050.1567 | K18: =('MODEL&SCHEDULE'!K$17-SENSITIVITY!J$85*SENSITIVITY!K$87+SENSITIVITY!J$85*SENSITIVITY!$I18)*(SENSITIVITY!K$88*(1-SENSITIVITY!$J$90)) -> 1128.15 | L18: =('MODEL&SCHEDULE'!L$17-SENSITIVITY!K$85*SENSITIVITY!L$87+SENSITIVITY!K$85*SENSITIVITY!$I18)*(SENSITIVITY!L$88*(1-SENSITIVITY!$J$90)) -> 1225.0141 | M18: =('MODEL&SCHEDULE'!M$17-SENSITIVITY!L$85*SENSITIVITY!M$87+SENSITIVITY!L$85*SENSITIVITY!$I18)*(SENSITIVITY!M$88*(1-SENSITIVITY!$J$90)) -> 1355.7071 | N18: =('MODEL&SCHEDULE'!N$17-SENSITIVITY!M$85*SENSITIVITY!N$87+SENSITIVITY!M$85*SENSITIVITY!$I18)*(SENSITIVITY!N$88*(1-SENSITIVITY!$J$90)) -> 1490.0362 | Q18: 0.04 | R18: 942.02745 | S18: 968.94252 | T18: 995.85759 | U18: 1021.6966 | V18: 1022.7727 | W18: 1049.6877 | X18: 1076.6028
I19: 0.1 | J19: =('MODEL&SCHEDULE'!J$17-SENSITIVITY!I$85*SENSITIVITY!J$87+SENSITIVITY!I$85*SENSITIVITY!$I19)*(SENSITIVITY!J$88*(1-SENSITIVITY!$J$90)) -> 1053.8389 | K19: =('MODEL&SCHEDULE'!K$17-SENSITIVITY!J$85*SENSITIVITY!K$87+SENSITIVITY!J$85*SENSITIVITY!$I19)*(SENSITIVITY!K$88*(1-SENSITIVITY!$J$90)) -> 1132.0174 | L19: =('MODEL&SCHEDULE'!L$17-SENSITIVITY!K$85*SENSITIVITY!L$87+SENSITIVITY!K$85*SENSITIVITY!$I19)*(SENSITIVITY!L$88*(1-SENSITIVITY!$J$90)) -> 1229.2692 | M19: =('MODEL&SCHEDULE'!M$17-SENSITIVITY!L$85*SENSITIVITY!M$87+SENSITIVITY!L$85*SENSITIVITY!$I19)*(SENSITIVITY!M$88*(1-SENSITIVITY!$J$90)) -> 1360.6616 | N19: =('MODEL&SCHEDULE'!N$17-SENSITIVITY!M$85*SENSITIVITY!N$87+SENSITIVITY!M$85*SENSITIVITY!$I19)*(SENSITIVITY!N$88*(1-SENSITIVITY!$J$90)) -> 1495.5873 | Q19: 0.05 | R19: 951.08541 | S19: 978.25928 | T19: 1005.4331 | U19: 1031.5206 | V19: 1032.607 | W19: 1059.7809 | X19: 1086.9548
I20: 0.11 | J20: =('MODEL&SCHEDULE'!J$17-SENSITIVITY!I$85*SENSITIVITY!J$87+SENSITIVITY!I$85*SENSITIVITY!$I20)*(SENSITIVITY!J$88*(1-SENSITIVITY!$J$90)) -> 1057.5211 | K20: =('MODEL&SCHEDULE'!K$17-SENSITIVITY!J$85*SENSITIVITY!K$87+SENSITIVITY!J$85*SENSITIVITY!$I20)*(SENSITIVITY!K$88*(1-SENSITIVITY!$J$90)) -> 1135.8848 | L20: =('MODEL&SCHEDULE'!L$17-SENSITIVITY!K$85*SENSITIVITY!L$87+SENSITIVITY!K$85*SENSITIVITY!$I20)*(SENSITIVITY!L$88*(1-SENSITIVITY!$J$90)) -> 1233.5243 | M20: =('MODEL&SCHEDULE'!M$17-SENSITIVITY!L$85*SENSITIVITY!M$87+SENSITIVITY!L$85*SENSITIVITY!$I20)*(SENSITIVITY!M$88*(1-SENSITIVITY!$J$90)) -> 1365.6161 | N20: =('MODEL&SCHEDULE'!N$17-SENSITIVITY!M$85*SENSITIVITY!N$87+SENSITIVITY!M$85*SENSITIVITY!$I20)*(SENSITIVITY!N$88*(1-SENSITIVITY!$J$90)) -> 1501.1384 | Q20: 0.06 | R20: 960.14336 | S20: 987.57603 | T20: 1015.0087 | U20: 1041.3446 | V20: 1042.4414 | W20: 1069.874 | X20: 1097.3067
I21: 0.12 | J21: =('MODEL&SCHEDULE'!J$17-SENSITIVITY!I$85*SENSITIVITY!J$87+SENSITIVITY!I$85*SENSITIVITY!$I21)*(SENSITIVITY!J$88*(1-SENSITIVITY!$J$90)) -> 1061.2033 | K21: =('MODEL&SCHEDULE'!K$17-SENSITIVITY!J$85*SENSITIVITY!K$87+SENSITIVITY!J$85*SENSITIVITY!$I21)*(SENSITIVITY!K$88*(1-SENSITIVITY!$J$90)) -> 1139.7522 | L21: =('MODEL&SCHEDULE'!L$17-SENSITIVITY!K$85*SENSITIVITY!L$87+SENSITIVITY!K$85*SENSITIVITY!$I21)*(SENSITIVITY!L$88*(1-SENSITIVITY!$J$90)) -> 1237.7793 | M21: =('MODEL&SCHEDULE'!M$17-SENSITIVITY!L$85*SENSITIVITY!M$87+SENSITIVITY!L$85*SENSITIVITY!$I21)*(SENSITIVITY!M$88*(1-SENSITIVITY!$J$90)) -> 1370.5706 | N21: =('MODEL&SCHEDULE'!N$17-SENSITIVITY!M$85*SENSITIVITY!N$87+SENSITIVITY!M$85*SENSITIVITY!$I21)*(SENSITIVITY!N$88*(1-SENSITIVITY!$J$90)) -> 1506.6896 | Q21: 0.07 | R21: 969.20132 | S21: 996.89279 | T21: 1024.5843 | U21: 1051.1686 | V21: 1052.2757 | W21: 1079.9672 | X21: 1107.6587
I22: 0.13 | J22: =('MODEL&SCHEDULE'!J$17-SENSITIVITY!I$85*SENSITIVITY!J$87+SENSITIVITY!I$85*SENSITIVITY!$I22)*(SENSITIVITY!J$88*(1-SENSITIVITY!$J$90)) -> 1064.8855 | K22: =('MODEL&SCHEDULE'!K$17-SENSITIVITY!J$85*SENSITIVITY!K$87+SENSITIVITY!J$85*SENSITIVITY!$I22)*(SENSITIVITY!K$88*(1-SENSITIVITY!$J$90)) -> 1143.6196 | L22: =('MODEL&SCHEDULE'!L$17-SENSITIVITY!K$85*SENSITIVITY!L$87+SENSITIVITY!K$85*SENSITIVITY!$I22)*(SENSITIVITY!L$88*(1-SENSITIVITY!$J$90)) -> 1242.0344 | M22: =('MODEL&SCHEDULE'!M$17-SENSITIVITY!L$85*SENSITIVITY!M$87+SENSITIVITY!L$85*SENSITIVITY!$I22)*(SENSITIVITY!M$88*(1-SENSITIVITY!$J$90)) -> 1375.5251 | N22: =('MODEL&SCHEDULE'!N$17-SENSITIVITY!M$85*SENSITIVITY!N$87+SENSITIVITY!M$85*SENSITIVITY!$I22)*(SENSITIVITY!N$88*(1-SENSITIVITY!$J$90)) -> 1512.2407 | Q22: 0.08 | R22: 978.25927 | S22: 1006.2095 | T22: 1034.1598 | U22: 1060.9927 | V22: 1062.1101 | W22: 1090.0603 | X22: 1118.0106
I23: 0.14 | J23: =('MODEL&SCHEDULE'!J$17-SENSITIVITY!I$85*SENSITIVITY!J$87+SENSITIVITY!I$85*SENSITIVITY!$I23)*(SENSITIVITY!J$88*(1-SENSITIVITY!$J$90)) -> 1068.5677 | K23: =('MODEL&SCHEDULE'!K$17-SENSITIVITY!J$85*SENSITIVITY!K$87+SENSITIVITY!J$85*SENSITIVITY!$I23)*(SENSITIVITY!K$88*(1-SENSITIVITY!$J$90)) -> 1147.487 | L23: =('MODEL&SCHEDULE'!L$17-SENSITIVITY!K$85*SENSITIVITY!L$87+SENSITIVITY!K$85*SENSITIVITY!$I23)*(SENSITIVITY!L$88*(1-SENSITIVITY!$J$90)) -> 1246.2895 | M23: =('MODEL&SCHEDULE'!M$17-SENSITIVITY!L$85*SENSITIVITY!M$87+SENSITIVITY!L$85*SENSITIVITY!$I23)*(SENSITIVITY!M$88*(1-SENSITIVITY!$J$90)) -> 1380.4796 | N23: =('MODEL&SCHEDULE'!N$17-SENSITIVITY!M$85*SENSITIVITY!N$87+SENSITIVITY!M$85*SENSITIVITY!$I23)*(SENSITIVITY!N$88*(1-SENSITIVITY!$J$90)) -> 1517.7918 | Q23: 0.09 | R23: 987.31723 | S23: 1015.5263 | T23: 1043.7354 | U23: 1070.8167 | V23: 1071.9444 | W23: 1100.1535 | X23: 1128.3626
... I26: 0.17 | J26: =('MODEL&SCHEDULE'!J$17-SENSITIVITY!I$85*SENSITIVITY!J$87+SENSITIVITY!I$85*SENSITIVITY!$I26)*(SENSITIVITY!J$88*(1-SENSITIVITY!$J$90)) -> 1079.6144 | K26: =('MODEL&SCHEDULE'!K$17-SENSITIVITY!J$85*SENSITIVITY!K$87+SENSITIVITY!J$85*SENSITIVITY!$I26)*(SENSITIVITY!K$88*(1-SENSITIVITY!$J$90)) -> 1159.0891 | L26: =('MODEL&SCHEDULE'!L$17-SENSITIVITY!K$85*SENSITIVITY!L$87+SENSITIVITY!K$85*SENSITIVITY!$I26)*(SENSITIVITY!L$88*(1-SENSITIVITY!$J$90)) -> 1259.0547 | M26: =('MODEL&SCHEDULE'!M$17-SENSITIVITY!L$85*SENSITIVITY!M$87+SENSITIVITY!L$85*SENSITIVITY!$I26)*(SENSITIVITY!M$88*(1-SENSITIVITY!$J$90)) -> 1395.343 | N26: =('MODEL&SCHEDULE'!N$17-SENSITIVITY!M$85*SENSITIVITY!N$87+SENSITIVITY!M$85*SENSITIVITY!$I26)*(SENSITIVITY!N$88*(1-SENSITIVITY!$J$90)) -> 1534.4452 | Q26: 0.12 | R26: 1014.4911 | S26: 1043.4766 | T26: 1072.462 | U26: 1100.2887 | V26: 1101.4475 | W26: 1130.4329 | X26: 1159.4184
B52: Tornado Chart Data + Chart
C53: Driver | D53: High Case | E53: Model Cases | F53: Low case | G53: Downside | H53: Upside | I53: range
C54: =C97 -> Revenue Growth | D54: 0.08 | E54: =J97 -> 0.054251228 | F54: -0.04
C55: =C88 -> EBIT margin | D55: 0.21066821 | E55: =J88 -> 0.18975078 | F55: 0.17066821
C56: =C89 -> Cost of sales as a % of revenue | D56: 0.54 | E56: =J89 -> 0.5608681 | F56: 0.58
C57: =C90 -> Reported ETR | D57: 0.24 | E57: =J90 -> 0.25 | F57: 0.26
C58: EBIT margin cal using Cost of sales | D58: =(1-D$56-$J$99) -> 0.21061888 | E58: =(1-E$56-$J$99) -> 0.18975078 | F58: =(1-F$56-$J$99) -> 0.17061888
C59: NOPAT | E59: =$I$96*(1+E54)*($E$55*(1-E57)) -> 1035.4279
C60: Revenue Growth | D60: =$I$96*(1+D$54)*($E$55*(1-$E$57)) -> 1060.7169 | F60: =$I$96*(1+F$54)*($E$55*(1-$E$57)) -> 942.85946 | G60: =F60-$E$59 -> -92.568398 | H60: =D60-$E$59 -> 25.289035 | I60: =H60-G60 -> 117.85743
C61: =C55 -> EBIT margin | D61: =$I$96*(1+$E$54)*(D$55*(1-$E$57)) -> 1149.5697 | F61: =$I$96*(1+$E$54)*(F$55*(1-$E$57)) -> 931.29853 | G61: =F61-$E$59 -> -104.12933 | H61: =D61-$E$59 -> 114.14179 | I61: =H61-G61 -> 218.27112
C62: =C56 -> Cost of sales as a % of revenue | D62: =$I$96*(1+$E$54)*(D$58*(1-$E$57)) -> 1149.3005 | F62: =$I$96*(1+$E$54)*(F$58*(1-$E$57)) -> 931.02935 | G62: =F62-$E$59 -> -104.39852 | H62: =D62-$E$59 -> 113.8726 | I62: =H62-G62 -> 218.27112
C63: =C57 -> Reported ETR | D63: =$I$96*(1+$E$54)*($E$55*(1-D$57)) -> 1049.2336 | F63: =$I$96*(1+$E$54)*($E$55*(1-F$57)) -> 1021.6222 | G63: =F63-$E$59 -> -13.805705 | H63: =D63-$E$59 -> 13.805705 | I63: =H63-G63 -> 27.61141
B66: Sorting
C67: =C61 -> EBIT margin | D67: =D61 -> 1149.5697 | F67: =F61 -> 931.29853 | G67: =G61 -> -104.12933 | H67: =H61 -> 114.14179 | I67: =I61 -> 218.27112
C68: =C60 -> Revenue Growth | D68: =D60 -> 1060.7169 | F68: =F60 -> 942.85946 | G68: =G60 -> -92.568398 | H68: =H60 -> 25.289035 | I68: =I60 -> 117.85743
C69: =C63 -> Reported ETR | D69: =D63 -> 1049.2336 | F69: =F63 -> 1021.6222 | G69: =G63 -> -13.805705 | H69: =H63 -> 13.805705 | I69: =I63 -> 27.61141
B72: Chart Input Table
C73: =C53 -> Driver | D73: =G53 -> Downside | E73: =H53 -> Upside
C74: =C67 -> EBIT margin | D74: =G67 -> -104.12933 | E74: =H67 -> 114.14179
C75: =C68 -> Revenue Growth | D75: =G68 -> -92.568398 | E75: =H68 -> 25.289035
C76: =C69 -> Reported ETR | D76: =G69 -> -13.805705 | E76: =H69 -> 13.805705
B84: INPUT
C85: ='MODEL&SCHEDULE'!C9 -> Online UK | D85: (Largest portion of Segmental Sales) | I85: ='MODEL&SCHEDULE'!I9 -> 2587.4 | J85: ='MODEL&SCHEDULE'!J9 -> 2716.77 | K85: ='MODEL&SCHEDULE'!K9 -> 2988.447 | L85: ='MODEL&SCHEDULE'!L9 -> 3478.5523 | M85: ='MODEL&SCHEDULE'!M9 -> 3895.9786 | N85: ='MODEL&SCHEDULE'!N9 -> 4207.6569
B86: Growth
C87: =SCENARIOS!C21 -> Online UK | J87: =SCENARIOS!J21 -> 0.05 | K87: =SCENARIOS!K21 -> 0.1 | L87: =SCENARIOS!L21 -> 0.164 | M87: =SCENARIOS!M21 -> 0.12 | N87: =SCENARIOS!N21 -> 0.08
C88: ='MODEL&SCHEDULE'!C77 -> EBIT margin | J88: ='MODEL&SCHEDULE'!J77 -> 0.18975078 | K88: ='MODEL&SCHEDULE'!K77 -> 0.18980313 | L88: ='MODEL&SCHEDULE'!L77 -> 0.18984527 | M88: ='MODEL&SCHEDULE'!M77 -> 0.18990605 | N88: ='MODEL&SCHEDULE'!N77 -> 0.18997823
C89: =ASSUMPTIONS!C55 -> Cost of sales as a % of revenue | J89: =ASSUMPTIONS!J55 -> 0.5608681
C90: =ASSUMPTIONS!C66 -> Reported ETR | J90: =ASSUMPTIONS!J66 -> 0.25
B91: OUTPUT
C92: ='MODEL&SCHEDULE'!C73 -> EBIAT/NOPAT | J92: ='MODEL&SCHEDULE'!J73 -> 1035.4279 | K92: ='MODEL&SCHEDULE'!K73 -> 1132.0174 | L92: ='MODEL&SCHEDULE'!L73 -> 1256.5016 | M92: ='MODEL&SCHEDULE'!M73 -> 1370.5706 | N92: ='MODEL&SCHEDULE'!N73 -> 1484.485
B94: Whole Business
B95: INPUT
C96: =SUMMARY!C8 -> Revenue | I96: =SUMMARY!I8 -> 6901.3 | J96: =SUMMARY!J8 -> 7275.704 | K96: =SUMMARY!K8 -> 7952.2216 | L96: =SUMMARY!L8 -> 8824.7422 | M96: =SUMMARY!M8 -> 9622.7977 | N96: =SUMMARY!N8 -> 10418.633
C97: =SUMMARY!C9 -> Revenue Growth | I97: =SUMMARY!I9 -> 0.1280136 | J97: =SUMMARY!J9 -> 0.054251228 | K97: =SUMMARY!K9 -> 0.092983118 | L97: =SUMMARY!L9 -> 0.10972036 | M97: =SUMMARY!M9 -> 0.090433853 | N97: =SUMMARY!N9 -> 0.082703069
C98: Gross Margin | J98: =1-E56 -> 0.4391319
C99: Opex Margin | J99: =('MODEL&SCHEDULE'!J21+'MODEL&SCHEDULE'!J22-'MODEL&SCHEDULE'!J25)/'MODEL&SCHEDULE'!J17 -> 0.24938112

Sheet DCF
C8: WACC from First Principles:

Sheet LBO ANALYSIS

Sheet REGRESSION

Sheet COMPS
C6: peers
C7: Sainsbury | E7: 0.156 | F7: 0.155 | G7: 0.152 | H7: 0.156 | I7: 0.158
C8: asda | E8: 0.144 | F8: 0.141 | G8: 0.138 | H8: 0.133 | I8: 0.123
C9: aldi | E9: 0.08 | F9: 0.086 | G9: 0.1 | H9: 0.1 | I9: 0.102
C10: morrisons | E10: 0.102 | F10: 0.097 | G10: 0.089 | H10: 0.087 | I10: 0.085
C11: lidl | E11: 0.053 | F11: 0.058 | G11: 0.067 | H11: 0.07 | I11: 0.073
C12: co-op | E12: 0.062 | F12: 0.059 | G12: 0.057 | H12: 0.054 | I12: 0.053
C13: waitrose | E13: 0.052 | F13: 0.049 | G13: 0.048 | H13: 0.047 | I13: 0.047
C14: iceland | E14: 0.025 | F14: 0.024 | G14: 0.024 | H14: 0.024 | I14: 0.023
C15: ocado | E15: 0.017 | F15: 0.017 | G15: 0.017 | H15: 0.018 | I15: 0.019

Sheet MONTE CARLO

Sheet CHECKS

Sheet DASHBOARD

Sheet SOTP

Sheet ACCOUNTING
B6: IFRS 16
B13: IAS 19
B20: IFRS 2
B26: INTANGIBLES

Sheet SOURCE
A4: 46177 | B4: =ASSUMPTIONS!C299 -> Risk- Free Rate % | C4: 46022 | D4: End year level of yield from British Government Stock, 10 year Nominal Par Yield IUAMNPY | E4: https://www.bankofengland.co.uk/boeapps/database/fromshowcolumns.asp?Travel=NIxIRxSUx&FromSeries=1&ToSeries=50&DAT=RNG&FD=1&FM=Jan&FY=2015&TD=31&TM=Dec&TY=2026&FNY=&CSVF=TT&VPD=Y&NewRevSince=Y&RFD=3&RFM=Jun&RFY=2007&html.x=222&html.y=43&C=DUS&C=DVI&Filter=Y&VUD=B | G4: https://www.bankofengland.co.uk/boeapps/database/fromshowcolumns.asp?Travel=NIxIRxSUx&FromSeries=1&ToSeries=50&DAT=RNG&FD=1&FM=Jan&FY=2015&TD=31&TM=Dec&TY=2026&FNY=&CSVF=TT&VPD=Y&NewRevSince=Y&RFD=3&RFM=Jun&RFY=2007&html.x=222&html.y=43&C=DUS&C=DVI&Filter=Y&VUD=B#
A5: =A4 -> 46177 | B5: =ASSUMPTIONS!C307 -> unlevered beta corrected for cash | C5: 46027 | E5: https://pages.stern.nyu.edu/~adamodar/New_Home_Page/datacurrent.html#discrate | G5: https://pages.stern.nyu.edu/~adamodar/pc/datasets/betaEurope.xls
A6: =A5 -> 46177 | B6: cost of equity (Europe) | C6: 0.091151863 | D6: retail(grocery and food) | E6: =E5 -> https://pages.stern.nyu.edu/~adamodar/New_Home_Page/datacurrent.html#discrate | G6: https://pages.stern.nyu.edu/~adamodar/pc/datasets/waccEurope.xls
A7: =A6 -> 46177 | B7: cost of capital(europe) | C7: 0.073766936 | D7: =D6 -> retail(grocery and food) | E7: =E6 -> https://pages.stern.nyu.edu/~adamodar/New_Home_Page/datacurrent.html#discrate | G7: https://pages.stern.nyu.edu/~adamodar/pc/datasets/waccEurope.xls
A8: =A7 -> 46177 | B8: =ASSUMPTIONS!C300 -> Equity Risk Premium % | C8: 46023 | D8: Risk Premiums for Other Markets | E8: =E7 -> https://pages.stern.nyu.edu/~adamodar/New_Home_Page/datacurrent.html#discrate | G8: https://pages.stern.nyu.edu/~adamodar/pc/datasets/ctryprem.xlsx
A9: =A8 -> 46177 | B9: =ASSUMPTIONS!#REF! -> #REF! | C9: 12weeks ending feb | D9: market share | E9: https://www.kantar.com/uki/campaigns/grocery-market-share
B10: =ASSUMPTIONS!#REF! -> #REF! | C10: February figure(Vol) | D10: Retail Sales Index time series | E10: https://www.ons.gov.uk/businessindustryandtrade/retailindustry/datasets/retailsales | G10: https://www.ons.gov.uk/file?uri=/businessindustryandtrade/retailindustry/datasets/retailsales/current/drsi.xlsx
B11: =ASSUMPTIONS!C32 -> UK CPI Inflation | C11: february | D11: %change over 12months | E11: https://www.ons.gov.uk/economy/inflationandpriceindices/datasets/consumerpriceinflation/current
A14: 46197 | B14: SONIA | C14: Daily rate | D14: Bank of England | E14: https://www.bankofengland.co.uk/boeapps/database/fromshowcolumns.asp?Travel=NIxSUx&FromSeries=1&ToSeries=50&DAT=RNG&FD=1&FM=Jan&FY=2014&TD=6&TM=Dec&TY=2040&FNY=&CSVF=TT&html.x=180&html.y=34&C=5JK&Filter=N

Sheet rough sheet
C2: PRACTICAL MODELLING DECISION: for your BASE CASE, assume the FULL £500m goes to buybacks (simplest, and the PRIMARY stated intention). Build a SCENARIO/SENSITIVITY toggle for "if share price exceeds £131, X% diverts to special dividend instead" if you want to show this risk — but it's not required for your base case.
W3: to to eliminate
W5: 2021
U7: ═══════════════════════════════════════════════════════
U8: SEGMENT REVENUE BUILD (feeds into the IS, shown as
U9: supporting schedule or top section)
U10: ═══════════════════════════════════════════════════════ | W10: 3284.1
U11: Online UK | W11: 250.3
U12: Online International | W12: =W10+W11 -> 3534.4
U13: NEXT Online subtotal | W13: 2231.7
U14: Next Retail | W14: 54.8
U15: Next Finance / credit interest | W15: =W12-W13-W14 -> 1247.9
U16: Total Platform | W16: 555.8
U17: Other business activities | W17: 246.8
U18: ───────────────────────────────────────────────────── | W18: -1.3
U19: TOTAL STATUTORY REVENUE [Check: 0] | W19: =W15-W16-W17+W18 -> 444
W20: 0.5
U21: YoY revenue growth %
W23: =SUM(W19:W22) -> 444.5
U24: ═══════════════════════════════════════════════════════
U25: COST OF SALES / GROSS PROFIT | W25: 0.6
U26: ═══════════════════════════════════════════════════════ | W26: -102.7
U27: Cost of sales | W27: =SUM(W23:W26) -> 342.4
U28: Expected credit loss (ECL) on Finance receivables | W28: -55.7
U29: ───────────────────────────────────────────────────── | W29: =SUM(W27:W28) -> 286.7
U30: GROSS PROFIT
U31: Gross margin %
U34: ═══════════════════════════════════════════════════════
U35: OPERATING EXPENSES | W35: =SUM(W33:W34) -> 0
U36: ═══════════════════════════════════════════════════════
U37: Distribution costs | W37: 223.3p
U38: Administrative expenses | W38: 221.9p
U39: (before exceptional items / adjusting items split out)
U40: ─────────────────────────────────────────────────────
U41: TRADING PROFIT
U44: ═══════════════════════════════════════════════════════
U45: BELOW TRADING PROFIT, ABOVE EBIT
U46: ═══════════════════════════════════════════════════════
U47: Share of profit from associates and joint ventures
U48: Impairment of associates/JV investments | W48: 444.5
U49: Exceptional items (curtailment, restructuring, etc.) | W49: -1
U50: ───────────────────────────────────────────────────── | W50: 136.8
U51: STATUTORY OPERATING PROFIT (EBIT) | W51: 196.6
U52: EBIT margin % | W52: 0.4
W53: 16.7
W54: -0.5
U55: ═══════════════════════════════════════════════════════ | W55: 1.1
U56: NORMALISATION ADJUSTMENTS (purple column — your | W56: -9.6
U57: adjusting items, shown as a bridge) | W57: 205.4
U58: ═══════════════════════════════════════════════════════ | W58: -29.5
U59: + Brand and customer relationship amortisation | W59: -22.9
U60: {=+ Share-based compensation charge} -> #NAME? | W60: =SUM(W48:W59) -> 938
U61: ± FX/derivative financial instrument gains/losses | W61: -113.2
U62: − Sale & leaseback gains | W62: =SUM(W60:W61) -> 824.8
U63: ± Net impairment reversal/charge on PP&E (non-run-rate)
U64: ± Net impairment reversal/charge on ROU assets (non-run-rate) | W64: -146.3
U65: − Government support income (e.g. JRS — historical only) | W65: 1.7
U66: − Lease modification/early exit gains | W66: =SUM(W64:W65) -> -144.6
U67: {=+ Curtailment loss (pension)} -> #NAME? | W67: 0.5
U68: + Associate impairment spike (above run-rate) | W68: 28.4
U69: {=+ Other investments write-off} -> #NAME? | W69: -16.7
U70: + Software impairment spike (above run-rate)
U71: ± Intangible disposal loss/gain (above run-rate)
U72: + One-off implementation/integration costs (M&A) | W72: 3.9
U73: ─────────────────────────────────────────────────────
U74: NORMALISED EBIT | W74: -2.4
U75: Normalised EBIT margin %
U78: ═══════════════════════════════════════════════════════ | W78: =SUM(W66:W76) -> -130.9
U79: EBITDA BRIDGE (shown as a separate block or schedule)
U80: ═══════════════════════════════════════════════════════ | W80: -19.3
U81: Normalised EBIT | W81: -189
U82: {=+ PP&E depreciation} -> #NAME? | W82: 162.7
U83: + ROU depreciation (IFRS 16)
U84: {=+ Software amortisation} -> #NAME?
U85: + Run-rate NCA impairment (PP&E, kept portion) | W85: -40
U86: + Run-rate NCA impairment (ROU, kept portion)
U87: + Run-rate software impairment (kept portion)
U88: ───────────────────────────────────────────────────── | W88: -171
U89: POST-IFRS 16 EBITDA | W89: -101.6
U90: Post-IFRS 16 EBITDA margin % | W90: 0.5
U92: − ROU depreciation
U93: + IFRS 16 lease interest (add back)
U94: ───────────────────────────────────────────────────── | W94: 126
U95: PRE-IFRS 16 EBITDA
U96: Pre-IFRS 16 EBITDA margin %
W97: =SUM(W80:W96) -> -231.7
W98: =W97+W78+W62 -> 462.2
U99: ═══════════════════════════════════════════════════════ | W99: 52.9
U100: FINANCE INCOME / COSTS
U101: ═══════════════════════════════════════════════════════ | W101: -0.3
U102: Finance income | W102: =SUM(W98:W101) -> 514.8
U103: Finance costs
U104: of which: interest on bank loans/bonds
U105: of which: IFRS 16 lease interest
U106: of which: discount unwind on provisions (strip if normalising)
U107: of which: pension net interest
U108: ─────────────────────────────────────────────────────
U109: NET FINANCE COST
W110: 474.8
W111: 60.5
...
